{
  "gizmos-infos": {
    "is2D": true,
    "is3DIcon": false,
    "iconSize": 2,
    "gridVisible": true,
    "gridColor": [
      150,
      150,
      150,
      255
    ],
    "isIconGizmo3D": false,
    "iconGizmoSize": 2,
    "isGridVisible": true,
    "transformToolName": "position",
    "pivot": "pivot",
    "coordinate": "local",
    "toolsVisibility3d": true
  },
  "float-window": {
    "position": {
      "cc": {
        "Camera": {
          "dock": false,
          "top": null,
          "bottom": 10,
          "left": null,
          "right": 10
        }
      }
    }
  },
  "camera": {
    "fov": 45,
    "far": 10000,
    "near": 0.01,
    "color": [
      48,
      48,
      48,
      255
    ],
    "wheelSpeed": 0.01,
    "wanderSpeed": 10,
    "enableAcceleration": true,
    "far2D": 10000,
    "near2D": 1,
    "wheelSpeed2D": 6,
    "size": "__default_design__",
    "iso": 0,
    "aperture": 19,
    "shutter": 7
  },
  "camera-infos": {
    "f46876e4-e81b-4931-b493-6d367be385e7": {
      "position": {
        "x": 361.3284132841328,
        "y": 247.97047970479707,
        "z": 5000
      },
      "rotation": {
        "x": 0,
        "y": 0,
        "z": 0,
        "w": 1
      },
      "viewCenter": {
        "x": 0,
        "y": 0,
        "z": 0
      }
    },
    "f003f78a-c18a-49b4-afe2-1f8df294b9b1": {
      "position": {
        "x": 1184.8713515748336,
        "y": 716.609613429333,
        "z": 5000
      },
      "rotation": {
        "x": 0,
        "y": 0,
        "z": 0,
        "w": 1
      },
      "viewCenter": {
        "x": 0,
        "y": 0,
        "z": 0
      }
    },
    "c77ecaa8-c936-46c4-a5b0-98692673ed87": {
      "position": {
        "x": 265.2104131037455,
        "y": 245.07360988476682,
        "z": 5000
      },
      "rotation": {
        "x": 0,
        "y": 0,
        "z": 0,
        "w": 1
      },
      "viewCenter": {
        "x": 0,
        "y": 0,
        "z": 0
      }
    },
    "dfsZ4/JBNAa5XmJMiITJ0B": {
      "position": {
        "x": 479,
        "y": 326.00000000000006,
        "z": 5000
      },
      "rotation": {
        "x": 0,
        "y": 0,
        "z": 0,
        "w": 1
      },
      "viewCenter": {
        "x": 0,
        "y": 0,
        "z": 0
      }
    },
    "84ghKwH2tHKZr6N83B2R4P": {
      "position": {
        "x": 680.564784814184,
        "y": 350.5980948017716,
        "z": 5000
      },
      "rotation": {
        "x": 0,
        "y": 0,
        "z": 0,
        "w": 1
      },
      "viewCenter": {
        "x": 0,
        "y": 0,
        "z": 0
      }
    },
    "deznPIp/BKz43/0RuddAPC": {
      "position": {
        "x": 479,
        "y": 326.00000000000006,
        "z": 5000
      },
      "rotation": {
        "x": 0,
        "y": 0,
        "z": 0,
        "w": 1
      },
      "viewCenter": {
        "x": 0,
        "y": 0,
        "z": 0
      }
    },
    "26wa6AnLhOs7HIQOrCkSjP": {
      "position": {
        "x": 479,
        "y": 326.00000000000006,
        "z": 5000
      },
      "rotation": {
        "x": 0,
        "y": 0,
        "z": 0,
        "w": 1
      },
      "viewCenter": {
        "x": 0,
        "y": 0,
        "z": 0
      }
    },
    "b5quJbwMtGBLT/OG5ujpPs": {
      "position": {
        "x": 479,
        "y": 326.00000000000006,
        "z": 5000
      },
      "rotation": {
        "x": 0,
        "y": 0,
        "z": 0,
        "w": 1
      },
      "viewCenter": {
        "x": 0,
        "y": 0,
        "z": 0
      }
    },
    "ffH3t/hGFAgrOjOAwno5gQ": {
      "position": {
        "x": 479,
        "y": 326.00000000000006,
        "z": 5000
      },
      "rotation": {
        "x": 0,
        "y": 0,
        "z": 0,
        "w": 1
      },
      "viewCenter": {
        "x": 0,
        "y": 0,
        "z": 0
      }
    },
    "6blM7hC79CgI4Wd0gPigRk": {
      "position": {
        "x": 479,
        "y": 326.00000000000006,
        "z": 5000
      },
      "rotation": {
        "x": 0,
        "y": 0,
        "z": 0,
        "w": 1
      },
      "viewCenter": {
        "x": 0,
        "y": 0,
        "z": 0
      }
    },
    "b2dpOU1MZHzZzN6mP9m3ti": {
      "position": {
        "x": 619.1651171927617,
        "y": 257.2314235276655,
        "z": 5000
      },
      "rotation": {
        "x": 0,
        "y": 0,
        "z": 0,
        "w": 1
      },
      "viewCenter": {
        "x": 0,
        "y": 0,
        "z": 0
      }
    },
    "5cXJvcvz1Hg6/AkN+oYWfQ": {
      "position": {
        "x": 307.24298591627667,
        "y": 52.40475632681239,
        "z": 5000
      },
      "rotation": {
        "x": 0,
        "y": 0,
        "z": 0,
        "w": 1
      },
      "viewCenter": {
        "x": 0,
        "y": 0,
        "z": 0
      }
    },
    "68FwF40bxIp5wm2FmPEYAt": {
      "position": {
        "x": 479,
        "y": 326.00000000000006,
        "z": 5000
      },
      "rotation": {
        "x": 0,
        "y": 0,
        "z": 0,
        "w": 1
      },
      "viewCenter": {
        "x": 0,
        "y": 0,
        "z": 0
      }
    },
    "84QyBAulFFB6iOrMMycGM6": {
      "position": {
        "x": 479,
        "y": 326.00000000000006,
        "z": 5000
      },
      "rotation": {
        "x": 0,
        "y": 0,
        "z": 0,
        "w": 1
      },
      "viewCenter": {
        "x": 0,
        "y": 0,
        "z": 0
      }
    },
    "16Jgx/kopAwKhkUTtMhnIZ": {
      "position": {
        "x": -253.3480541262188,
        "y": -72.69141170577927,
        "z": 5000
      },
      "rotation": {
        "x": 0,
        "y": 0,
        "z": 0,
        "w": 1
      },
      "viewCenter": {
        "x": 0,
        "y": 0,
        "z": 0
      }
    },
    "19pKlzDcREaLtGqIwqnG1+": {
      "position": {
        "x": 479,
        "y": 326.00000000000006,
        "z": 5000
      },
      "rotation": {
        "x": 0,
        "y": 0,
        "z": 0,
        "w": 1
      },
      "viewCenter": {
        "x": 0,
        "y": 0,
        "z": 0
      }
    },
    "8bU5PCrS5Nm6RhFR9wXGnq": {
      "position": {
        "x": 330.3373213337443,
        "y": 206.07280118604956,
        "z": 5000
      },
      "rotation": {
        "x": 0,
        "y": 0,
        "z": 0,
        "w": 1
      },
      "viewCenter": {
        "x": 0,
        "y": 0,
        "z": 0
      }
    },
    "02RuceaV1IFa7gJoMmVUp6": {
      "position": {
        "x": 438.67128581762,
        "y": 316.5725083729499,
        "z": 5000
      },
      "rotation": {
        "x": 0,
        "y": 0,
        "z": 0,
        "w": 1
      },
      "viewCenter": {
        "x": 0,
        "y": 0,
        "z": 0
      }
    },
    "2bzeAQSWhNVpuhj00xICzi": {
      "position": {
        "x": 479,
        "y": 326.00000000000006,
        "z": 5000
      },
      "rotation": {
        "x": 0,
        "y": 0,
        "z": 0,
        "w": 1
      },
      "viewCenter": {
        "x": 0,
        "y": 0,
        "z": 0
      }
    },
    "bcxbpKf/pBfpOzllBgnKjJ": {
      "position": {
        "x": 479,
        "y": 326.00000000000006,
        "z": 5000
      },
      "rotation": {
        "x": 0,
        "y": 0,
        "z": 0,
        "w": 1
      },
      "viewCenter": {
        "x": 0,
        "y": 0,
        "z": 0
      }
    },
    "892k69SmxCV5GPzMuvEK/v": {
      "position": {
        "x": 476.8859390517013,
        "y": 347.84529646575317,
        "z": 5000
      },
      "rotation": {
        "x": 0,
        "y": 0,
        "z": 0,
        "w": 1
      },
      "viewCenter": {
        "x": 0,
        "y": 0,
        "z": 0
      }
    },
    "cb3d96cd-d6f4-4f89-9460-b9f2f3cbf9c2": {
      "position": {
        "x": 640,
        "y": 360,
        "z": 5000
      },
      "rotation": {
        "x": 0,
        "y": 0,
        "z": 0,
        "w": 1
      },
      "viewCenter": {
        "x": 0,
        "y": 0,
        "z": 0
      },
      "contentRect": {
        "x": 350,
        "y": 195,
        "width": 580,
        "height": 330
      },
      "scale": 1
    },
    "040499d5-e9f5-46cf-9423-f575207e4159": {
      "position": {
        "x": 579.5219186120635,
        "y": 323.41217061977056,
        "z": 5000
      },
      "rotation": {
        "x": 0,
        "y": 0,
        "z": 0,
        "w": 1
      },
      "viewCenter": {
        "x": 0,
        "y": 0,
        "z": 0
      },
      "contentRect": {
        "x": -341.6523573029709,
        "y": -101.7451874948607,
        "width": 948,
        "height": 437.53846153846155
      },
      "scale": 0.5145606128972277
    },
    "82c78f5e-5e73-47eb-bff6-5470d68bd74f": {
      "position": {
        "x": 640,
        "y": 360,
        "z": 5000
      },
      "rotation": {
        "x": 0,
        "y": 0,
        "z": 0,
        "w": 1
      },
      "viewCenter": {
        "x": 0,
        "y": 0,
        "z": 0
      },
      "contentRect": {
        "x": -140,
        "y": 0,
        "width": 948,
        "height": 437.53846153846155
      },
      "scale": 0.6076923076923078
    },
    "6104e8f6-0564-43f7-9c7c-c0cb3d2a9054": {
      "position": {
        "x": 724.7629626019686,
        "y": 253.2907177226576,
        "z": 5000
      },
      "rotation": {
        "x": 0,
        "y": 0,
        "z": 0,
        "w": 1
      },
      "viewCenter": {
        "x": 0,
        "y": 0,
        "z": 0
      },
      "contentRect": {
        "x": 518.644444692498,
        "y": 158.15909407213277,
        "width": 290,
        "height": 133.84615384615384
      },
      "scale": 0.7034787629497977
    },
    "fc3c5944-03ea-49ff-9194-231e2f9ee56e": {
      "position": {
        "x": 779.1195550021763,
        "y": 1480.1321257507018,
        "z": 5000
      },
      "rotation": {
        "x": 0,
        "y": 0,
        "z": 0,
        "w": 1
      },
      "viewCenter": {
        "x": 0,
        "y": 0,
        "z": 0
      }
    },
    "160bd486-554c-4599-838b-fd29668553ff": {
      "position": {
        "x": 545.9144386259834,
        "y": 279.73549853318576,
        "z": 5000
      },
      "rotation": {
        "x": 0,
        "y": 0,
        "z": 0,
        "w": 1
      },
      "viewCenter": {
        "x": 0,
        "y": 0,
        "z": 0
      },
      "contentRect": {
        "x": -370.69939152612017,
        "y": -344.09771363713946,
        "width": 948,
        "height": 437.53846153846155
      },
      "scale": 0.5145606128972136
    },
    "6cBlHnI6lPKZSg0ZMjXSd5": {
      "position": {
        "x": 479,
        "y": 326.00000000000006,
        "z": 5000
      },
      "rotation": {
        "x": 0,
        "y": 0,
        "z": 0,
        "w": 1
      },
      "viewCenter": {
        "x": 0,
        "y": 0,
        "z": 0
      }
    },
    "401I8hXgVCH4yDHQr7as7l": {
      "position": {
        "x": 549.5751605765598,
        "y": 602.5449854146211,
        "z": 5000
      },
      "rotation": {
        "x": 0,
        "y": 0,
        "z": 0,
        "w": 1
      },
      "viewCenter": {
        "x": 0,
        "y": 0,
        "z": 0
      }
    },
    "b45xCEXiRN3qlBGIUZLcJw": {
      "position": {
        "x": 623.3728003541296,
        "y": 316.09198057378944,
        "z": 5000
      },
      "rotation": {
        "x": 0,
        "y": 0,
        "z": 0,
        "w": 1
      },
      "viewCenter": {
        "x": 0,
        "y": 0,
        "z": 0
      }
    },
    "87HdPW0/9CBa8fQSLY38wS": {
      "position": {
        "x": 479,
        "y": 326.00000000000006,
        "z": 5000
      },
      "rotation": {
        "x": 0,
        "y": 0,
        "z": 0,
        "w": 1
      },
      "viewCenter": {
        "x": 0,
        "y": 0,
        "z": 0
      }
    },
    "feRfm1KPJNwZ5rYWB3U+mi": {
      "position": {
        "x": 548.0347023098199,
        "y": 548.922239623173,
        "z": 5000
      },
      "rotation": {
        "x": 0,
        "y": 0,
        "z": 0,
        "w": 1
      },
      "viewCenter": {
        "x": 0,
        "y": 0,
        "z": 0
      }
    },
    "2b+0DRYYFLQp7HuqdIPq1/": {
      "position": {
        "x": 470.2695814979631,
        "y": 1011.0145386468671,
        "z": 5000
      },
      "rotation": {
        "x": 0,
        "y": 0,
        "z": 0,
        "w": 1
      },
      "viewCenter": {
        "x": 0,
        "y": 0,
        "z": 0
      }
    },
    "92D1aONVJFi65peek2cGYG": {
      "position": {
        "x": 640.5,
        "y": 360.5,
        "z": 5000
      },
      "rotation": {
        "x": 0,
        "y": 0,
        "z": 0,
        "w": 1
      },
      "viewCenter": {
        "x": 0,
        "y": 0,
        "z": 0
      }
    },
    "b20JmH15JBZoNksCOrQPQD": {
      "position": {
        "x": 479,
        "y": 326.00000000000006,
        "z": 5000
      },
      "rotation": {
        "x": 0,
        "y": 0,
        "z": 0,
        "w": 1
      },
      "viewCenter": {
        "x": 0,
        "y": 0,
        "z": 0
      }
    },
    "e5D6aq6gZMZaWwoNITsKSC": {
      "position": {
        "x": 479,
        "y": 326.00000000000006,
        "z": 5000
      },
      "rotation": {
        "x": 0,
        "y": 0,
        "z": 0,
        "w": 1
      },
      "viewCenter": {
        "x": 0,
        "y": 0,
        "z": 0
      }
    },
    "b9gh02mi1HqKGDUOotv2zh": {
      "position": {
        "x": 881.6853864437269,
        "y": 1201.119565923504,
        "z": 5000
      },
      "rotation": {
        "x": 0,
        "y": 0,
        "z": 0,
        "w": 1
      },
      "viewCenter": {
        "x": 0,
        "y": 0,
        "z": 0
      }
    },
    "986XsL8G1AxqcsB31LOnhb": {
      "position": {
        "x": 599.6252252736855,
        "y": 459.80063064983466,
        "z": 5000
      },
      "rotation": {
        "x": 0,
        "y": 0,
        "z": 0,
        "w": 1
      },
      "viewCenter": {
        "x": 0,
        "y": 0,
        "z": 0
      }
    },
    "ddBspuGOJNRaMi/aeMWJIm": {
      "position": {
        "x": 588.5377709570716,
        "y": 785.6469403943385,
        "z": 5000
      },
      "rotation": {
        "x": 0,
        "y": 0,
        "z": 0,
        "w": 1
      },
      "viewCenter": {
        "x": 0,
        "y": 0,
        "z": 0
      }
    },
    "46lqzLYOFFVbGrMxk3csUg": {
      "position": {
        "x": 1123.2606436398878,
        "y": 1112.4576142604913,
        "z": 5000
      },
      "rotation": {
        "x": 0,
        "y": 0,
        "z": 0,
        "w": 1
      },
      "viewCenter": {
        "x": 0,
        "y": 0,
        "z": 0
      }
    },
    "3178PJfNpHO4BR5YsoLRTO": {
      "position": {
        "x": 647.750533920177,
        "y": 1073.9963707940105,
        "z": 5000
      },
      "rotation": {
        "x": 0,
        "y": 0,
        "z": 0,
        "w": 1
      },
      "viewCenter": {
        "x": 0,
        "y": 0,
        "z": 0
      }
    },
    "bbjZ/qbz5AsqELwv/e1eLU": {
      "position": {
        "x": 872.5544678257683,
        "y": 996.8517665987835,
        "z": 5000
      },
      "rotation": {
        "x": 0,
        "y": 0,
        "z": 0,
        "w": 1
      },
      "viewCenter": {
        "x": 0,
        "y": 0,
        "z": 0
      }
    },
    "5elPsWg49AhrvWSoUzUbjj": {
      "position": {
        "x": 481.0201587611218,
        "y": 699.7489936717534,
        "z": 5000
      },
      "rotation": {
        "x": 0,
        "y": 0,
        "z": 0,
        "w": 1
      },
      "viewCenter": {
        "x": 0,
        "y": 0,
        "z": 0
      }
    },
    "85ZHc8ct1II7VUJaAlfU45": {
      "position": {
        "x": 564.9763189349425,
        "y": 957.4641451522489,
        "z": 5000
      },
      "rotation": {
        "x": 0,
        "y": 0,
        "z": 0,
        "w": 1
      },
      "viewCenter": {
        "x": 0,
        "y": 0,
        "z": 0
      }
    },
    "ef4s0NqjlKRYOdvjW133Jh": {
      "position": {
        "x": 479,
        "y": 326,
        "z": 5000
      },
      "rotation": {
        "x": 0,
        "y": 0,
        "z": 0,
        "w": 1
      },
      "viewCenter": {
        "x": 0,
        "y": 0,
        "z": 0
      }
    },
    "6dY/K0c/tI655iXCLt1kjF": {
      "position": {
        "x": 1318.0111199574055,
        "y": 838.070013241429,
        "z": 5000
      },
      "rotation": {
        "x": 0,
        "y": 0,
        "z": 0,
        "w": 1
      },
      "viewCenter": {
        "x": 0,
        "y": 0,
        "z": 0
      }
    },
    "03L8liTglGnoNlSMqvDdCe": {
      "position": {
        "x": -166.750338222741,
        "y": 177.71934055854535,
        "z": 5000
      },
      "rotation": {
        "x": 0,
        "y": 0,
        "z": 0,
        "w": 1
      },
      "viewCenter": {
        "x": 0,
        "y": 0,
        "z": 0
      }
    },
    "c2eZfBtttBsY56N/cbLl+K": {
      "position": {
        "x": 479,
        "y": 326.00000000000006,
        "z": 5000
      },
      "rotation": {
        "x": 0,
        "y": 0,
        "z": 0,
        "w": 1
      },
      "viewCenter": {
        "x": 0,
        "y": 0,
        "z": 0
      }
    },
    "5aQ4KL1dlIybYu92sOjacK": {
      "position": {
        "x": -63.99894957180777,
        "y": 1278.104136229956,
        "z": 5000
      },
      "rotation": {
        "x": 0,
        "y": 0,
        "z": 0,
        "w": 1
      },
      "viewCenter": {
        "x": 0,
        "y": 0,
        "z": 0
      }
    },
    "96KZFDGeJJpZ5BXv0YuL/j": {
      "position": {
        "x": 479,
        "y": 326,
        "z": 5000
      },
      "rotation": {
        "x": 0,
        "y": 0,
        "z": 0,
        "w": 1
      },
      "viewCenter": {
        "x": 0,
        "y": 0,
        "z": 0
      }
    },
    "39lCP5lZlMMJteT4LXKh7Y": {
      "position": {
        "x": 479,
        "y": 326.00000000000006,
        "z": 5000
      },
      "rotation": {
        "x": 0,
        "y": 0,
        "z": 0,
        "w": 1
      },
      "viewCenter": {
        "x": 0,
        "y": 0,
        "z": 0
      }
    },
    "ae5zuZOStFdrPFVkV0//dz": {
      "position": {
        "x": 250.7377189404151,
        "y": 979.7331536757862,
        "z": 5000
      },
      "rotation": {
        "x": 0,
        "y": 0,
        "z": 0,
        "w": 1
      },
      "viewCenter": {
        "x": 0,
        "y": 0,
        "z": 0
      }
    },
    "a9cHCQ7/5K7aqBXdtxHBhN": {
      "position": {
        "x": 354.6408359972678,
        "y": 1442.0405192420506,
        "z": 5000
      },
      "rotation": {
        "x": 0,
        "y": 0,
        "z": 0,
        "w": 1
      },
      "viewCenter": {
        "x": 0,
        "y": 0,
        "z": 0
      }
    },
    "177Wt6VylFVq4Yir4wDVf5": {
      "position": {
        "x": 324.1518732987498,
        "y": 892.9896648034062,
        "z": 5000
      },
      "rotation": {
        "x": 0,
        "y": 0,
        "z": 0,
        "w": 1
      },
      "viewCenter": {
        "x": 0,
        "y": 0,
        "z": 0
      }
    },
    "368oKVy1xC2rVPZ6pMOu4C": {
      "position": {
        "x": 428.01389668413424,
        "y": 1201.1084774592557,
        "z": 5000
      },
      "rotation": {
        "x": 0,
        "y": 0,
        "z": 0,
        "w": 1
      },
      "viewCenter": {
        "x": 0,
        "y": 0,
        "z": 0
      }
    },
    "6cN/To0PND0pXBmcm1vPRx": {
      "position": {
        "x": 588.6684166616255,
        "y": 686.6064544022804,
        "z": 5000
      },
      "rotation": {
        "x": 0,
        "y": 0,
        "z": 0,
        "w": 1
      },
      "viewCenter": {
        "x": 0,
        "y": 0,
        "z": 0
      }
    },
    "2ankIpVSBGg7ZL5MLO8NCg": {
      "position": {
        "x": 626.4310291750577,
        "y": 1296.3774550813391,
        "z": 5000
      },
      "rotation": {
        "x": 0,
        "y": 0,
        "z": 0,
        "w": 1
      },
      "viewCenter": {
        "x": 0,
        "y": 0,
        "z": 0
      }
    },
    "80HY/5/IdAa6cyHQrGiOBR": {
      "position": {
        "x": 156.01990018384345,
        "y": 852.4135249170909,
        "z": 5000
      },
      "rotation": {
        "x": 0,
        "y": 0,
        "z": 0,
        "w": 1
      },
      "viewCenter": {
        "x": 0,
        "y": 0,
        "z": 0
      }
    },
    "f0KqKgphxKaKa8RMEqylNe": {
      "position": {
        "x": 510.1153123597155,
        "y": 1456.0523524436594,
        "z": 5000
      },
      "rotation": {
        "x": 0,
        "y": 0,
        "z": 0,
        "w": 1
      },
      "viewCenter": {
        "x": 0,
        "y": 0,
        "z": 0
      }
    },
    "6dIstPhYpJc66cfU9NEfbC": {
      "position": {
        "x": 665.2384809337042,
        "y": 868.1257709323409,
        "z": 5000
      },
      "rotation": {
        "x": 0,
        "y": 0,
        "z": 0,
        "w": 1
      },
      "viewCenter": {
        "x": 0,
        "y": 0,
        "z": 0
      }
    },
    "814C+SSUJFWrk9cViAQIB7": {
      "position": {
        "x": 651.5764956025399,
        "y": 986.3620984310922,
        "z": 5000
      },
      "rotation": {
        "x": 0,
        "y": 0,
        "z": 0,
        "w": 1
      },
      "viewCenter": {
        "x": 0,
        "y": 0,
        "z": 0
      }
    },
    "83ZzAi7pJDLoXrtns88wb1": {
      "position": {
        "x": 601.1739467533044,
        "y": 790.1205335842349,
        "z": 5000
      },
      "rotation": {
        "x": 0,
        "y": 0,
        "z": 0,
        "w": 1
      },
      "viewCenter": {
        "x": 0,
        "y": 0,
        "z": 0
      }
    },
    "13SHb7KzRDHq5Ldkq+/Z5v": {
      "position": {
        "x": 306.0463035246994,
        "y": 1447.7667343727298,
        "z": 5000
      },
      "rotation": {
        "x": 0,
        "y": 0,
        "z": 0,
        "w": 1
      },
      "viewCenter": {
        "x": 0,
        "y": 0,
        "z": 0
      }
    },
    "8fTRxXyPVHB6WEznp/e0ak": {
      "position": {
        "x": 460.6156769658809,
        "y": 788.4404092534121,
        "z": 5000
      },
      "rotation": {
        "x": 0,
        "y": 0,
        "z": 0,
        "w": 1
      },
      "viewCenter": {
        "x": 0,
        "y": 0,
        "z": 0
      }
    },
    "e6mTn9NiFA15cEZOrqhDVG": {
      "position": {
        "x": 521.5232178422675,
        "y": 1314.609170634781,
        "z": 5000
      },
      "rotation": {
        "x": 0,
        "y": 0,
        "z": 0,
        "w": 1
      },
      "viewCenter": {
        "x": 0,
        "y": 0,
        "z": 0
      }
    },
    "7faTPNar9NmLm/P4neY6lD": {
      "position": {
        "x": 692.7236700150241,
        "y": 602.9352755291533,
        "z": 5000
      },
      "rotation": {
        "x": 0,
        "y": 0,
        "z": 0,
        "w": 1
      },
      "viewCenter": {
        "x": 0,
        "y": 0,
        "z": 0
      }
    },
    "fdum6JaBFNE5PnSpnuFq33": {
      "position": {
        "x": 364.0068389269884,
        "y": 1148.328530392274,
        "z": 5000
      },
      "rotation": {
        "x": 0,
        "y": 0,
        "z": 0,
        "w": 1
      },
      "viewCenter": {
        "x": 0,
        "y": 0,
        "z": 0
      }
    },
    "4bXJLzk/JA26y6vXD1ara+": {
      "position": {
        "x": 682.1138237463572,
        "y": 863.125478151205,
        "z": 5000
      },
      "rotation": {
        "x": 0,
        "y": 0,
        "z": 0,
        "w": 1
      },
      "viewCenter": {
        "x": 0,
        "y": 0,
        "z": 0
      }
    },
    "degBZHi8RC/L0PIr1ddlW0": {
      "position": {
        "x": 320.8964198257813,
        "y": 1342.4922824747393,
        "z": 5000
      },
      "rotation": {
        "x": 0,
        "y": 0,
        "z": 0,
        "w": 1
      },
      "viewCenter": {
        "x": 0,
        "y": 0,
        "z": 0
      }
    },
    "bbxhG1kVRDs5NxEunnS3w8": {
      "position": {
        "x": 884.323590482169,
        "y": 933.68477501899,
        "z": 5000
      },
      "rotation": {
        "x": 0,
        "y": 0,
        "z": 0,
        "w": 1
      },
      "viewCenter": {
        "x": 0,
        "y": 0,
        "z": 0
      }
    },
    "84HLdsW9VEo5oB+DejIAmc": {
      "position": {
        "x": 563.2493011064687,
        "y": 1642.4183571716515,
        "z": 5000
      },
      "rotation": {
        "x": 0,
        "y": 0,
        "z": 0,
        "w": 1
      },
      "viewCenter": {
        "x": 0,
        "y": 0,
        "z": 0
      }
    },
    "adbtWV2ZVMIrvkfK9qpVu2": {
      "position": {
        "x": 412.09279745457593,
        "y": 869.7061379913512,
        "z": 5000
      },
      "rotation": {
        "x": 0,
        "y": 0,
        "z": 0,
        "w": 1
      },
      "viewCenter": {
        "x": 0,
        "y": 0,
        "z": 0
      }
    },
    "d6NkcDJIdDH6hfvTcgvNZ3": {
      "position": {
        "x": 600.5530763687742,
        "y": 1529.3947210596843,
        "z": 5000
      },
      "rotation": {
        "x": 0,
        "y": 0,
        "z": 0,
        "w": 1
      },
      "viewCenter": {
        "x": 0,
        "y": 0,
        "z": 0
      }
    },
    "d7FCi+uMxJvap24WGZvyqJ": {
      "position": {
        "x": 260.28704315194886,
        "y": 913.3909728921789,
        "z": 5000
      },
      "rotation": {
        "x": 0,
        "y": 0,
        "z": 0,
        "w": 1
      },
      "viewCenter": {
        "x": 0,
        "y": 0,
        "z": 0
      }
    },
    "05XfGkh2VLRL0eafxTNvPY": {
      "position": {
        "x": 412.25977714459896,
        "y": 1444.8124856234497,
        "z": 5000
      },
      "rotation": {
        "x": 0,
        "y": 0,
        "z": 0,
        "w": 1
      },
      "viewCenter": {
        "x": 0,
        "y": 0,
        "z": 0
      }
    },
    "1dwQ7EtzpC6KnlvhGwTrVB": {
      "position": {
        "x": 261.4837608356893,
        "y": 850.8636348773454,
        "z": 5000
      },
      "rotation": {
        "x": 0,
        "y": 0,
        "z": 0,
        "w": 1
      },
      "viewCenter": {
        "x": 0,
        "y": 0,
        "z": 0
      }
    },
    "564cWMO9BDOIOEZ7RifKDl": {
      "position": {
        "x": 703.2549109249106,
        "y": 1557.1065312499004,
        "z": 5000
      },
      "rotation": {
        "x": 0,
        "y": 0,
        "z": 0,
        "w": 1
      },
      "viewCenter": {
        "x": 0,
        "y": 0,
        "z": 0
      }
    },
    "28u6otKTBIorBrHedLZ308": {
      "position": {
        "x": 817.0797800194327,
        "y": 476.9587455797474,
        "z": 5000
      },
      "rotation": {
        "x": 0,
        "y": 0,
        "z": 0,
        "w": 1
      },
      "viewCenter": {
        "x": 0,
        "y": 0,
        "z": 0
      }
    },
    "9bPFHhESVHUYBXkh0TSUZM": {
      "position": {
        "x": 961.0645189066404,
        "y": 1454.399075642255,
        "z": 5000
      },
      "rotation": {
        "x": 0,
        "y": 0,
        "z": 0,
        "w": 1
      },
      "viewCenter": {
        "x": 0,
        "y": 0,
        "z": 0
      }
    },
    "00becqDE1Mx6xYZE/UgrW+": {
      "position": {
        "x": 500.42504665571414,
        "y": 853.3185412824093,
        "z": 5000
      },
      "rotation": {
        "x": 0,
        "y": 0,
        "z": 0,
        "w": 1
      },
      "viewCenter": {
        "x": 0,
        "y": 0,
        "z": 0
      }
    },
    "a9GRfjSb1DKqwEeC4s4XBa": {
      "position": {
        "x": 685.7378149699371,
        "y": 1329.6539609643455,
        "z": 5000
      },
      "rotation": {
        "x": 0,
        "y": 0,
        "z": 0,
        "w": 1
      },
      "viewCenter": {
        "x": 0,
        "y": 0,
        "z": 0
      }
    },
    "84ozs0pgJNhJzOpvfw+z1L": {
      "position": {
        "x": 634.1673911449282,
        "y": 735.8933699380898,
        "z": 5000
      },
      "rotation": {
        "x": 0,
        "y": 0,
        "z": 0,
        "w": 1
      },
      "viewCenter": {
        "x": 0,
        "y": 0,
        "z": 0
      }
    },
    "81OOkbtSlDx5mdAzaIgsHq": {
      "position": {
        "x": 361.8082189979588,
        "y": 1538.6827874637204,
        "z": 5000
      },
      "rotation": {
        "x": 0,
        "y": 0,
        "z": 0,
        "w": 1
      },
      "viewCenter": {
        "x": 0,
        "y": 0,
        "z": 0
      }
    },
    "de/S9PnSdOi6rI/y/bj2RC": {
      "position": {
        "x": 285.1007308701811,
        "y": 722.9982891406294,
        "z": 5000
      },
      "rotation": {
        "x": 0,
        "y": 0,
        "z": 0,
        "w": 1
      },
      "viewCenter": {
        "x": 0,
        "y": 0,
        "z": 0
      }
    },
    "11ShnP2OJBLpeu/qTb19eA": {
      "position": {
        "x": 838.9635193964591,
        "y": 902.1261331250472,
        "z": 5000
      },
      "rotation": {
        "x": 0,
        "y": 0,
        "z": 0,
        "w": 1
      },
      "viewCenter": {
        "x": 0,
        "y": 0,
        "z": 0
      }
    },
    "cbYT3J9eFCCYfd7zB/3oz6": {
      "position": {
        "x": 756.5233406683228,
        "y": 636.2383806953093,
        "z": 5000
      },
      "rotation": {
        "x": 0,
        "y": 0,
        "z": 0,
        "w": 1
      },
      "viewCenter": {
        "x": 0,
        "y": 0,
        "z": 0
      }
    },
    "2eqPMMW2tDpJoFq0nsyr1r": {
      "position": {
        "x": 479,
        "y": 326.00000000000006,
        "z": 5000
      },
      "rotation": {
        "x": 0,
        "y": 0,
        "z": 0,
        "w": 1
      },
      "viewCenter": {
        "x": 0,
        "y": 0,
        "z": 0
      }
    },
    "c9BkHEmjtKzIxsOXEJf8W8": {
      "position": {
        "x": 479,
        "y": 326.00000000000006,
        "z": 5000
      },
      "rotation": {
        "x": 0,
        "y": 0,
        "z": 0,
        "w": 1
      },
      "viewCenter": {
        "x": 0,
        "y": 0,
        "z": 0
      }
    },
    "4fHbAZX9ROvbOl2hd0R0pm": {
      "position": {
        "x": 479,
        "y": 326.00000000000006,
        "z": 5000
      },
      "rotation": {
        "x": 0,
        "y": 0,
        "z": 0,
        "w": 1
      },
      "viewCenter": {
        "x": 0,
        "y": 0,
        "z": 0
      }
    },
    "9eZ8aKgbJOGbbiDEGvXVY7": {
      "position": {
        "x": 806.1186790257368,
        "y": 599.9825913534688,
        "z": 5000
      },
      "rotation": {
        "x": 0,
        "y": 0,
        "z": 0,
        "w": 1
      },
      "viewCenter": {
        "x": 0,
        "y": 0,
        "z": 0
      }
    },
    "fb7Y2WFL5HUq+FGL1XKRmz": {
      "position": {
        "x": 945.169732488777,
        "y": 1282.5419303002727,
        "z": 5000
      },
      "rotation": {
        "x": 0,
        "y": 0,
        "z": 0,
        "w": 1
      },
      "viewCenter": {
        "x": 0,
        "y": 0,
        "z": 0
      }
    },
    "1egsjInmNC9LorQuB/3JNt": {
      "position": {
        "x": 818.1671890885168,
        "y": 1025.8293761501543,
        "z": 5000
      },
      "rotation": {
        "x": 0,
        "y": 0,
        "z": 0,
        "w": 1
      },
      "viewCenter": {
        "x": 0,
        "y": 0,
        "z": 0
      }
    },
    "4e/F7vxRlNeZpkAhsH6mBB": {
      "position": {
        "x": 479,
        "y": 326.00000000000006,
        "z": 5000
      },
      "rotation": {
        "x": 0,
        "y": 0,
        "z": 0,
        "w": 1
      },
      "viewCenter": {
        "x": 0,
        "y": 0,
        "z": 0
      }
    },
    "836/7PjNRP140dfo43V6LO": {
      "position": {
        "x": 607.637881122123,
        "y": 264.6300229668807,
        "z": 5000
      },
      "rotation": {
        "x": 0,
        "y": 0,
        "z": 0,
        "w": 1
      },
      "viewCenter": {
        "x": 0,
        "y": 0,
        "z": 0
      }
    },
    "07iPDsELNDY5HXJsxZpLPM": {
      "position": {
        "x": 839.5161435972568,
        "y": 852.2001072068036,
        "z": 5000
      },
      "rotation": {
        "x": 0,
        "y": 0,
        "z": 0,
        "w": 1
      },
      "viewCenter": {
        "x": 0,
        "y": 0,
        "z": 0
      }
    },
    "18sjIVhaRONZbhVesPrTpq": {
      "position": {
        "x": 479,
        "y": 326.00000000000006,
        "z": 5000
      },
      "rotation": {
        "x": 0,
        "y": 0,
        "z": 0,
        "w": 1
      },
      "viewCenter": {
        "x": 0,
        "y": 0,
        "z": 0
      }
    },
    "bfVx+LuGBOr5vY1/QtZuLQ": {
      "position": {
        "x": 479,
        "y": 326.00000000000006,
        "z": 5000
      },
      "rotation": {
        "x": 0,
        "y": 0,
        "z": 0,
        "w": 1
      },
      "viewCenter": {
        "x": 0,
        "y": 0,
        "z": 0
      }
    },
    "23+VE3dvlJur+xv9FTnLnD": {
      "position": {
        "x": 479,
        "y": 326.00000000000006,
        "z": 5000
      },
      "rotation": {
        "x": 0,
        "y": 0,
        "z": 0,
        "w": 1
      },
      "viewCenter": {
        "x": 0,
        "y": 0,
        "z": 0
      }
    },
    "e36uRRpRxLKL0fTU8FceAu": {
      "position": {
        "x": 528.6061930013165,
        "y": 484.3303674645646,
        "z": 5000
      },
      "rotation": {
        "x": 0,
        "y": 0,
        "z": 0,
        "w": 1
      },
      "viewCenter": {
        "x": 0,
        "y": 0,
        "z": 0
      }
    },
    "11aeKkaOpLeryPrOo5SBEI": {
      "position": {
        "x": 479,
        "y": 326.00000000000006,
        "z": 5000
      },
      "rotation": {
        "x": 0,
        "y": 0,
        "z": 0,
        "w": 1
      },
      "viewCenter": {
        "x": 0,
        "y": 0,
        "z": 0
      }
    },
    "113UBKyXJLp6D6XzS67lZw": {
      "position": {
        "x": 479,
        "y": 326.00000000000006,
        "z": 5000
      },
      "rotation": {
        "x": 0,
        "y": 0,
        "z": 0,
        "w": 1
      },
      "viewCenter": {
        "x": 0,
        "y": 0,
        "z": 0
      }
    },
    "a0KllkMsBD4KL6cKTCVMT7": {
      "position": {
        "x": 959.6752480895008,
        "y": 946.2986583949604,
        "z": 5000
      },
      "rotation": {
        "x": 0,
        "y": 0,
        "z": 0,
        "w": 1
      },
      "viewCenter": {
        "x": 0,
        "y": 0,
        "z": 0
      }
    },
    "d3m0Kblb1HerlslaVuPYNl": {
      "position": {
        "x": 479,
        "y": 326.0000000000001,
        "z": 5000
      },
      "rotation": {
        "x": 0,
        "y": 0,
        "z": 0,
        "w": 1
      },
      "viewCenter": {
        "x": 0,
        "y": 0,
        "z": 0
      }
    },
    "c2Bu17F+9PI5FCIrKAyVGO": {
      "position": {
        "x": 479,
        "y": 326.00000000000006,
        "z": 5000
      },
      "rotation": {
        "x": 0,
        "y": 0,
        "z": 0,
        "w": 1
      },
      "viewCenter": {
        "x": 0,
        "y": 0,
        "z": 0
      }
    },
    "c7J9JENUdD6JphodvDhzWm": {
      "position": {
        "x": 479,
        "y": 326.00000000000006,
        "z": 5000
      },
      "rotation": {
        "x": 0,
        "y": 0,
        "z": 0,
        "w": 1
      },
      "viewCenter": {
        "x": 0,
        "y": 0,
        "z": 0
      }
    },
    "28O+HNenBExZzpgMFaBYwY": {
      "position": {
        "x": 479,
        "y": 326.00000000000006,
        "z": 5000
      },
      "rotation": {
        "x": 0,
        "y": 0,
        "z": 0,
        "w": 1
      },
      "viewCenter": {
        "x": 0,
        "y": 0,
        "z": 0
      }
    },
    "bfQ4NmiZxC65xG5bBgIyJW": {
      "position": {
        "x": 199.86426322402156,
        "y": 738.2571196344167,
        "z": 5000
      },
      "rotation": {
        "x": 0,
        "y": 0,
        "z": 0,
        "w": 1
      },
      "viewCenter": {
        "x": 0,
        "y": 0,
        "z": 0
      }
    },
    "35acHG+TdA2q9IAyoCJ4v6": {
      "position": {
        "x": 415.0551434738181,
        "y": 1604.3083453736187,
        "z": 5000
      },
      "rotation": {
        "x": 0,
        "y": 0,
        "z": 0,
        "w": 1
      },
      "viewCenter": {
        "x": 0,
        "y": 0,
        "z": 0
      }
    },
    "94VMSrablCxq32SdYVp+Hr": {
      "position": {
        "x": 1601.6856671937603,
        "y": 904.3718879864533,
        "z": 5000
      },
      "rotation": {
        "x": 0,
        "y": 0,
        "z": 0,
        "w": 1
      },
      "viewCenter": {
        "x": 0,
        "y": 0,
        "z": 0
      }
    },
    "cepyzQYSFHurtB20e2oiTg": {
      "position": {
        "x": 897.9631184940346,
        "y": 1400.4059632316912,
        "z": 5000
      },
      "rotation": {
        "x": 0,
        "y": 0,
        "z": 0,
        "w": 1
      },
      "viewCenter": {
        "x": 0,
        "y": 0,
        "z": 0
      }
    },
    "992p6YL0dNjbT7kZw4/+k3": {
      "position": {
        "x": 673.908228226619,
        "y": 451.5907042224916,
        "z": 5000
      },
      "rotation": {
        "x": 0,
        "y": 0,
        "z": 0,
        "w": 1
      },
      "viewCenter": {
        "x": 0,
        "y": 0,
        "z": 0
      }
    },
    "28Y5qmjS1O9paqNA5fXW6w": {
      "position": {
        "x": 900.6719824099755,
        "y": 460.9988897657055,
        "z": 5000
      },
      "rotation": {
        "x": 0,
        "y": 0,
        "z": 0,
        "w": 1
      },
      "viewCenter": {
        "x": 0,
        "y": 0,
        "z": 0
      }
    },
    "166cgh1T1PQr+68EYXKahz": {
      "position": {
        "x": 479,
        "y": 326,
        "z": 5000
      },
      "rotation": {
        "x": 0,
        "y": 0,
        "z": 0,
        "w": 1
      },
      "viewCenter": {
        "x": 0,
        "y": 0,
        "z": 0
      }
    },
    "7c7OqKiiZNYKVjJhVZFMNv": {
      "position": {
        "x": 479,
        "y": 326.00000000000006,
        "z": 5000
      },
      "rotation": {
        "x": 0,
        "y": 0,
        "z": 0,
        "w": 1
      },
      "viewCenter": {
        "x": 0,
        "y": 0,
        "z": 0
      }
    },
    "feA7EwLddIJKTVKmmh1D80": {
      "position": {
        "x": 613.345546099202,
        "y": 763.9948904222889,
        "z": 5000
      },
      "rotation": {
        "x": 0,
        "y": 0,
        "z": 0,
        "w": 1
      },
      "viewCenter": {
        "x": 0,
        "y": 0,
        "z": 0
      }
    },
    "64WpnXXFxAxoT/SBT40WOj": {
      "position": {
        "x": 479,
        "y": 326.00000000000006,
        "z": 5000
      },
      "rotation": {
        "x": 0,
        "y": 0,
        "z": 0,
        "w": 1
      },
      "viewCenter": {
        "x": 0,
        "y": 0,
        "z": 0
      }
    },
    "c3H33I1b1IFqCoZ99yOm0N": {
      "position": {
        "x": 734.4562669197519,
        "y": 476.8797939948762,
        "z": 5000
      },
      "rotation": {
        "x": 0,
        "y": 0,
        "z": 0,
        "w": 1
      },
      "viewCenter": {
        "x": 0,
        "y": 0,
        "z": 0
      }
    },
    "8dfs4oRvtEx7Qjx63g9IwM": {
      "position": {
        "x": 994.3926462951979,
        "y": 1207.5794623546533,
        "z": 5000
      },
      "rotation": {
        "x": 0,
        "y": 0,
        "z": 0,
        "w": 1
      },
      "viewCenter": {
        "x": 0,
        "y": 0,
        "z": 0
      }
    },
    "3eUDF5rlhDCa3+WZdeNdl/": {
      "position": {
        "x": 479,
        "y": 326,
        "z": 5000
      },
      "rotation": {
        "x": 0,
        "y": 0,
        "z": 0,
        "w": 1
      },
      "viewCenter": {
        "x": 0,
        "y": 0,
        "z": 0
      }
    },
    "c7t6B9hPxOLL5LMmYjafjr": {
      "position": {
        "x": 479,
        "y": 326.00000000000006,
        "z": 5000
      },
      "rotation": {
        "x": 0,
        "y": 0,
        "z": 0,
        "w": 1
      },
      "viewCenter": {
        "x": 0,
        "y": 0,
        "z": 0
      }
    },
    "3fxOVbCWRG9KSqBqKlvF21": {
      "position": {
        "x": 788.1271793081731,
        "y": 1249.3272213087726,
        "z": 5000
      },
      "rotation": {
        "x": 0,
        "y": 0,
        "z": 0,
        "w": 1
      },
      "viewCenter": {
        "x": 0,
        "y": 0,
        "z": 0
      }
    },
    "deIIq06q5JA4GlvNcB0kEr": {
      "position": {
        "x": 770.1417354563736,
        "y": 729.6213966926612,
        "z": 5000
      },
      "rotation": {
        "x": 0,
        "y": 0,
        "z": 0,
        "w": 1
      },
      "viewCenter": {
        "x": 0,
        "y": 0,
        "z": 0
      }
    },
    "d3NMG+pe9PzKzD9y8Ui+82": {
      "position": {
        "x": 600.7499905596633,
        "y": 750.1273534680751,
        "z": 5000
      },
      "rotation": {
        "x": 0,
        "y": 0,
        "z": 0,
        "w": 1
      },
      "viewCenter": {
        "x": 0,
        "y": 0,
        "z": 0
      }
    },
    "82acrKxJFOxraEZeRPpUAR": {
      "position": {
        "x": 1810.4774664182191,
        "y": 689.0620992112006,
        "z": 5000
      },
      "rotation": {
        "x": 0,
        "y": 0,
        "z": 0,
        "w": 1
      },
      "viewCenter": {
        "x": 0,
        "y": 0,
        "z": 0
      }
    },
    "faKiZxy9lFrLlD/0k71QvQ": {
      "position": {
        "x": 524.3008323396143,
        "y": 309.1625224932408,
        "z": 5000
      },
      "rotation": {
        "x": 0,
        "y": 0,
        "z": 0,
        "w": 1
      },
      "viewCenter": {
        "x": 0,
        "y": 0,
        "z": 0
      }
    },
    "b73J2ydSlFTIMyTaeVnIeV": {
      "position": {
        "x": 715.9147990854558,
        "y": 861.0057599958162,
        "z": 5000
      },
      "rotation": {
        "x": 0,
        "y": 0,
        "z": 0,
        "w": 1
      },
      "viewCenter": {
        "x": 0,
        "y": 0,
        "z": 0
      }
    },
    "2e5FSaiM1Ec7FG+3K8limu": {
      "position": {
        "x": 536.4930865639178,
        "y": 530.8203732390516,
        "z": 5000
      },
      "rotation": {
        "x": 0,
        "y": 0,
        "z": 0,
        "w": 1
      },
      "viewCenter": {
        "x": 0,
        "y": 0,
        "z": 0
      }
    },
    "21U374PzVKw632XzVr2r5z": {
      "position": {
        "x": 479,
        "y": 326.00000000000006,
        "z": 5000
      },
      "rotation": {
        "x": 0,
        "y": 0,
        "z": 0,
        "w": 1
      },
      "viewCenter": {
        "x": 0,
        "y": 0,
        "z": 0
      }
    },
    "eah9i90ENFY5uKGhnLRIh4": {
      "position": {
        "x": 626.3391343786647,
        "y": 1018.5493615582262,
        "z": 5000
      },
      "rotation": {
        "x": 0,
        "y": 0,
        "z": 0,
        "w": 1
      },
      "viewCenter": {
        "x": 0,
        "y": 0,
        "z": 0
      }
    },
    "8c9RNF/7NIgoya4WVDfby1": {
      "position": {
        "x": 508.09139155418046,
        "y": 761.0357178612893,
        "z": 5000
      },
      "rotation": {
        "x": 0,
        "y": 0,
        "z": 0,
        "w": 1
      },
      "viewCenter": {
        "x": 0,
        "y": 0,
        "z": 0
      }
    },
    "a8n80xPZhAq5FcGQxHcAaD": {
      "position": {
        "x": 842.3760071019698,
        "y": 790.6410426060052,
        "z": 5000
      },
      "rotation": {
        "x": 0,
        "y": 0,
        "z": 0,
        "w": 1
      },
      "viewCenter": {
        "x": 0,
        "y": 0,
        "z": 0
      }
    },
    "a0cnn+mzFFvJtwll646g8g": {
      "position": {
        "x": 1087.7054903528347,
        "y": 1185.0389619571731,
        "z": 5000
      },
      "rotation": {
        "x": 0,
        "y": 0,
        "z": 0,
        "w": 1
      },
      "viewCenter": {
        "x": 0,
        "y": 0,
        "z": 0
      }
    },
    "cbA6hQZW1PGLL9w+ZRH5r7": {
      "position": {
        "x": 619.0836694935805,
        "y": 774.5130655474929,
        "z": 5000
      },
      "rotation": {
        "x": 0,
        "y": 0,
        "z": 0,
        "w": 1
      },
      "viewCenter": {
        "x": 0,
        "y": 0,
        "z": 0
      }
    },
    "76uUZ+fu5CVpDD3cjz40SR": {
      "position": {
        "x": -192.9874768301504,
        "y": 582.2345215592109,
        "z": 5000
      },
      "rotation": {
        "x": 0,
        "y": 0,
        "z": 0,
        "w": 1
      },
      "viewCenter": {
        "x": 0,
        "y": 0,
        "z": 0
      }
    },
    "06fx80xOpAs7SSfPADkMrS": {
      "position": {
        "x": 479,
        "y": 326.00000000000006,
        "z": 5000
      },
      "rotation": {
        "x": 0,
        "y": 0,
        "z": 0,
        "w": 1
      },
      "viewCenter": {
        "x": 0,
        "y": 0,
        "z": 0
      }
    },
    "ab60qW1ilAF5WwNrDQnS3k": {
      "position": {
        "x": 479,
        "y": 326.00000000000006,
        "z": 5000
      },
      "rotation": {
        "x": 0,
        "y": 0,
        "z": 0,
        "w": 1
      },
      "viewCenter": {
        "x": 0,
        "y": 0,
        "z": 0
      }
    },
    "ffLz3rldVOmJg5nn2FQnhf": {
      "position": {
        "x": 479,
        "y": 326.00000000000006,
        "z": 5000
      },
      "rotation": {
        "x": 0,
        "y": 0,
        "z": 0,
        "w": 1
      },
      "viewCenter": {
        "x": 0,
        "y": 0,
        "z": 0
      }
    },
    "73nGB4+uJHdJ4OQPjDR2Is": {
      "position": {
        "x": 479,
        "y": 326.00000000000006,
        "z": 5000
      },
      "rotation": {
        "x": 0,
        "y": 0,
        "z": 0,
        "w": 1
      },
      "viewCenter": {
        "x": 0,
        "y": 0,
        "z": 0
      }
    },
    "28/LbzRmxCArEuDBGO27I8": {
      "position": {
        "x": 479,
        "y": 326.00000000000006,
        "z": 5000
      },
      "rotation": {
        "x": 0,
        "y": 0,
        "z": 0,
        "w": 1
      },
      "viewCenter": {
        "x": 0,
        "y": 0,
        "z": 0
      }
    },
    "c6PPG25SNOVJaPxSeVtJ4w": {
      "position": {
        "x": 479,
        "y": 326.00000000000006,
        "z": 5000
      },
      "rotation": {
        "x": 0,
        "y": 0,
        "z": 0,
        "w": 1
      },
      "viewCenter": {
        "x": 0,
        "y": 0,
        "z": 0
      }
    },
    "b4R6sYXqFBN7aJq4ik7v7L": {
      "position": {
        "x": 479,
        "y": 326.00000000000006,
        "z": 5000
      },
      "rotation": {
        "x": 0,
        "y": 0,
        "z": 0,
        "w": 1
      },
      "viewCenter": {
        "x": 0,
        "y": 0,
        "z": 0
      }
    },
    "20Bb3fO0BNAKYCRl3I4vZ/": {
      "position": {
        "x": 479,
        "y": 326.00000000000006,
        "z": 5000
      },
      "rotation": {
        "x": 0,
        "y": 0,
        "z": 0,
        "w": 1
      },
      "viewCenter": {
        "x": 0,
        "y": 0,
        "z": 0
      }
    },
    "c1B1j59eZBMpbQL2sLVWE2": {
      "position": {
        "x": 479,
        "y": 326.00000000000006,
        "z": 5000
      },
      "rotation": {
        "x": 0,
        "y": 0,
        "z": 0,
        "w": 1
      },
      "viewCenter": {
        "x": 0,
        "y": 0,
        "z": 0
      }
    },
    "d9JcTWQntKqYBBTSGzp90N": {
      "position": {
        "x": 479,
        "y": 326.00000000000006,
        "z": 5000
      },
      "rotation": {
        "x": 0,
        "y": 0,
        "z": 0,
        "w": 1
      },
      "viewCenter": {
        "x": 0,
        "y": 0,
        "z": 0
      }
    },
    "848lpVjZpG6IZct2/BMJrD": {
      "position": {
        "x": 984.8031746625335,
        "y": 267.16717189167525,
        "z": 5000
      },
      "rotation": {
        "x": 0,
        "y": 0,
        "z": 0,
        "w": 1
      },
      "viewCenter": {
        "x": 0,
        "y": 0,
        "z": 0
      }
    },
    "eab264hIZHyImJTLp298Ix": {
      "position": {
        "x": 556.0380874445921,
        "y": 279.8472967571554,
        "z": 5000
      },
      "rotation": {
        "x": 0,
        "y": 0,
        "z": 0,
        "w": 1
      },
      "viewCenter": {
        "x": 0,
        "y": 0,
        "z": 0
      }
    },
    "6ehEz/vehN/LfWbWZ2vhX5": {
      "position": {
        "x": 663.5087957897385,
        "y": 882.5344749133794,
        "z": 5000
      },
      "rotation": {
        "x": 0,
        "y": 0,
        "z": 0,
        "w": 1
      },
      "viewCenter": {
        "x": 0,
        "y": 0,
        "z": 0
      }
    },
    "55zp+PNZ9FvaP9yYhBrnKu": {
      "position": {
        "x": 479,
        "y": 326,
        "z": 5000
      },
      "rotation": {
        "x": 0,
        "y": 0,
        "z": 0,
        "w": 1
      },
      "viewCenter": {
        "x": 0,
        "y": 0,
        "z": 0
      }
    },
    "a2F3cK8wRBOLlYKqjDeTcb": {
      "position": {
        "x": 479,
        "y": 326.00000000000006,
        "z": 5000
      },
      "rotation": {
        "x": 0,
        "y": 0,
        "z": 0,
        "w": 1
      },
      "viewCenter": {
        "x": 0,
        "y": 0,
        "z": 0
      }
    },
    "1cUNag9xhCup2oh3+BUxAo": {
      "position": {
        "x": 673.6749924692339,
        "y": 739.0292169981482,
        "z": 5000
      },
      "rotation": {
        "x": 0,
        "y": 0,
        "z": 0,
        "w": 1
      },
      "viewCenter": {
        "x": 0,
        "y": 0,
        "z": 0
      }
    },
    "31IzfMAh1HYZ2GwOw+4LgQ": {
      "position": {
        "x": 635.1214299519195,
        "y": 814.2939943178246,
        "z": 5000
      },
      "rotation": {
        "x": 0,
        "y": 0,
        "z": 0,
        "w": 1
      },
      "viewCenter": {
        "x": 0,
        "y": 0,
        "z": 0
      }
    },
    "1eIaTSvzZByKFHrGlkfFCZ": {
      "position": {
        "x": 931.6497266075936,
        "y": 665.5542273026773,
        "z": 5000
      },
      "rotation": {
        "x": 0,
        "y": 0,
        "z": 0,
        "w": 1
      },
      "viewCenter": {
        "x": 0,
        "y": 0,
        "z": 0
      }
    },
    "87zaRDqhZJBY/LljPGSIK2": {
      "position": {
        "x": 828.2098115393171,
        "y": 1236.677863367418,
        "z": 5000
      },
      "rotation": {
        "x": 0,
        "y": 0,
        "z": 0,
        "w": 1
      },
      "viewCenter": {
        "x": 0,
        "y": 0,
        "z": 0
      }
    },
    "690AF/qExEP5dwr8w6saFN": {
      "position": {
        "x": 479,
        "y": 326,
        "z": 5000
      },
      "rotation": {
        "x": 0,
        "y": 0,
        "z": 0,
        "w": 1
      },
      "viewCenter": {
        "x": 0,
        "y": 0,
        "z": 0
      }
    },
    "3c9QTtthpKGrR130HJqGMg": {
      "position": {
        "x": 479,
        "y": 326.00000000000006,
        "z": 5000
      },
      "rotation": {
        "x": 0,
        "y": 0,
        "z": 0,
        "w": 1
      },
      "viewCenter": {
        "x": 0,
        "y": 0,
        "z": 0
      }
    },
    "7bctpkZJxD/43/UbYeNmEA": {
      "position": {
        "x": 492.67976218365936,
        "y": 508.3968291154584,
        "z": 5000
      },
      "rotation": {
        "x": 0,
        "y": 0,
        "z": 0,
        "w": 1
      },
      "viewCenter": {
        "x": 0,
        "y": 0,
        "z": 0
      }
    },
    "5cSmBiIMhHNJWugr+/hNxc": {
      "position": {
        "x": 952.3931012793387,
        "y": 561.070258645721,
        "z": 5000
      },
      "rotation": {
        "x": 0,
        "y": 0,
        "z": 0,
        "w": 1
      },
      "viewCenter": {
        "x": 0,
        "y": 0,
        "z": 0
      }
    },
    "a2wEct6OZOSqtWytDp33nd": {
      "position": {
        "x": 479,
        "y": 325.5,
        "z": 5000
      },
      "rotation": {
        "x": 0,
        "y": 0,
        "z": 0,
        "w": 1
      },
      "viewCenter": {
        "x": 0,
        "y": 0,
        "z": 0
      }
    },
    "39i7sfEvBFLLW7Grl3UpCb": {
      "position": {
        "x": 479,
        "y": 325.5,
        "z": 5000
      },
      "rotation": {
        "x": 0,
        "y": 0,
        "z": 0,
        "w": 1
      },
      "viewCenter": {
        "x": 0,
        "y": 0,
        "z": 0
      }
    },
    "2bFuHmKVNP17yni52pG1dY": {
      "position": {
        "x": 479,
        "y": 325.5,
        "z": 5000
      },
      "rotation": {
        "x": 0,
        "y": 0,
        "z": 0,
        "w": 1
      },
      "viewCenter": {
        "x": 0,
        "y": 0,
        "z": 0
      }
    },
    "300WUR2iFEa7mijNg9NUpA": {
      "position": {
        "x": 479,
        "y": 325.5,
        "z": 5000
      },
      "rotation": {
        "x": 0,
        "y": 0,
        "z": 0,
        "w": 1
      },
      "viewCenter": {
        "x": 0,
        "y": 0,
        "z": 0
      }
    },
    "aa368eSptBZa0qtF7tL2SR": {
      "position": {
        "x": 479,
        "y": 325.5,
        "z": 5000
      },
      "rotation": {
        "x": 0,
        "y": 0,
        "z": 0,
        "w": 1
      },
      "viewCenter": {
        "x": 0,
        "y": 0,
        "z": 0
      }
    },
    "3bRTwEsmpExbGxy2ARcRwp": {
      "position": {
        "x": 338.2828238846459,
        "y": 275.61664857328753,
        "z": 5000
      },
      "rotation": {
        "x": 0,
        "y": 0,
        "z": 0,
        "w": 1
      },
      "viewCenter": {
        "x": 0,
        "y": 0,
        "z": 0
      }
    },
    "20VMsglxROArNEErDve3nf": {
      "position": {
        "x": 479,
        "y": 325.5,
        "z": 5000
      },
      "rotation": {
        "x": 0,
        "y": 0,
        "z": 0,
        "w": 1
      },
      "viewCenter": {
        "x": 0,
        "y": 0,
        "z": 0
      }
    },
    "6e8br9hEtE7K1uD5qTTSQ7": {
      "position": {
        "x": 479,
        "y": 325.5,
        "z": 5000
      },
      "rotation": {
        "x": 0,
        "y": 0,
        "z": 0,
        "w": 1
      },
      "viewCenter": {
        "x": 0,
        "y": 0,
        "z": 0
      }
    },
    "aedG8Kp0RMxJ/4UQ87KWU1": {
      "position": {
        "x": 479,
        "y": 325.5,
        "z": 5000
      },
      "rotation": {
        "x": 0,
        "y": 0,
        "z": 0,
        "w": 1
      },
      "viewCenter": {
        "x": 0,
        "y": 0,
        "z": 0
      }
    },
    "e2lmofYpBLYKLfdx7CBkDA": {
      "position": {
        "x": 479,
        "y": 325.5,
        "z": 5000
      },
      "rotation": {
        "x": 0,
        "y": 0,
        "z": 0,
        "w": 1
      },
      "viewCenter": {
        "x": 0,
        "y": 0,
        "z": 0
      }
    },
    "61Z6oU9TNNu7yrMYLfEXFr": {
      "position": {
        "x": 479,
        "y": 325.5,
        "z": 5000
      },
      "rotation": {
        "x": 0,
        "y": 0,
        "z": 0,
        "w": 1
      },
      "viewCenter": {
        "x": 0,
        "y": 0,
        "z": 0
      }
    },
    "6eO8Md+gFBEZgVJcIrmk0s": {
      "position": {
        "x": 479,
        "y": 325.5,
        "z": 5000
      },
      "rotation": {
        "x": 0,
        "y": 0,
        "z": 0,
        "w": 1
      },
      "viewCenter": {
        "x": 0,
        "y": 0,
        "z": 0
      }
    },
    "20XMwzdxtCOZuoWBwSplUD": {
      "position": {
        "x": 479,
        "y": 325.5,
        "z": 5000
      },
      "rotation": {
        "x": 0,
        "y": 0,
        "z": 0,
        "w": 1
      },
      "viewCenter": {
        "x": 0,
        "y": 0,
        "z": 0
      }
    },
    "10fr11Wd5KnYqu4euaLuk7": {
      "position": {
        "x": 479,
        "y": 325.5,
        "z": 5000
      },
      "rotation": {
        "x": 0,
        "y": 0,
        "z": 0,
        "w": 1
      },
      "viewCenter": {
        "x": 0,
        "y": 0,
        "z": 0
      }
    },
    "ee1K00kclFcri1jZC8mIUl": {
      "position": {
        "x": 479,
        "y": 325.5,
        "z": 5000
      },
      "rotation": {
        "x": 0,
        "y": 0,
        "z": 0,
        "w": 1
      },
      "viewCenter": {
        "x": 0,
        "y": 0,
        "z": 0
      }
    },
    "e7FXg6pVBFm4e4xw/G+9y5": {
      "position": {
        "x": 479,
        "y": 325.5,
        "z": 5000
      },
      "rotation": {
        "x": 0,
        "y": 0,
        "z": 0,
        "w": 1
      },
      "viewCenter": {
        "x": 0,
        "y": 0,
        "z": 0
      }
    },
    "bf16AsbspO5JmgpAV5Lkti": {
      "position": {
        "x": 479,
        "y": 325.5,
        "z": 5000
      },
      "rotation": {
        "x": 0,
        "y": 0,
        "z": 0,
        "w": 1
      },
      "viewCenter": {
        "x": 0,
        "y": 0,
        "z": 0
      }
    },
    "e1IqKgEo9OWqUVJBJuGaQK": {
      "position": {
        "x": 479,
        "y": 325.5,
        "z": 5000
      },
      "rotation": {
        "x": 0,
        "y": 0,
        "z": 0,
        "w": 1
      },
      "viewCenter": {
        "x": 0,
        "y": 0,
        "z": 0
      }
    },
    "0bgr/po6BN66uFOxSZ0zVc": {
      "position": {
        "x": 479,
        "y": 325.5,
        "z": 5000
      },
      "rotation": {
        "x": 0,
        "y": 0,
        "z": 0,
        "w": 1
      },
      "viewCenter": {
        "x": 0,
        "y": 0,
        "z": 0
      }
    },
    "9a+E61mXBOtb56A2+4ayib": {
      "position": {
        "x": 479,
        "y": 325.5,
        "z": 5000
      },
      "rotation": {
        "x": 0,
        "y": 0,
        "z": 0,
        "w": 1
      },
      "viewCenter": {
        "x": 0,
        "y": 0,
        "z": 0
      }
    },
    "d5nVqfb7lFQpv8i6s6ZrJq": {
      "position": {
        "x": 479,
        "y": 325.5,
        "z": 5000
      },
      "rotation": {
        "x": 0,
        "y": 0,
        "z": 0,
        "w": 1
      },
      "viewCenter": {
        "x": 0,
        "y": 0,
        "z": 0
      }
    },
    "66SIp46P5PhanbCU54vQz4": {
      "position": {
        "x": 479,
        "y": 325.5,
        "z": 5000
      },
      "rotation": {
        "x": 0,
        "y": 0,
        "z": 0,
        "w": 1
      },
      "viewCenter": {
        "x": 0,
        "y": 0,
        "z": 0
      }
    },
    "95IDAkznlGiLpX6+OoD0Md": {
      "position": {
        "x": 479,
        "y": 325.5,
        "z": 5000
      },
      "rotation": {
        "x": 0,
        "y": 0,
        "z": 0,
        "w": 1
      },
      "viewCenter": {
        "x": 0,
        "y": 0,
        "z": 0
      }
    },
    "d1CF7yjahG27WFbAWdXl99": {
      "position": {
        "x": 479,
        "y": 325.5,
        "z": 5000
      },
      "rotation": {
        "x": 0,
        "y": 0,
        "z": 0,
        "w": 1
      },
      "viewCenter": {
        "x": 0,
        "y": 0,
        "z": 0
      }
    },
    "29N1tyrbRA+7GLP2dO/C9R": {
      "position": {
        "x": 479,
        "y": 325.5,
        "z": 5000
      },
      "rotation": {
        "x": 0,
        "y": 0,
        "z": 0,
        "w": 1
      },
      "viewCenter": {
        "x": 0,
        "y": 0,
        "z": 0
      }
    },
    "dfgn0Dqn5O3Ibk2YbpUAMF": {
      "position": {
        "x": 479,
        "y": 325.5,
        "z": 5000
      },
      "rotation": {
        "x": 0,
        "y": 0,
        "z": 0,
        "w": 1
      },
      "viewCenter": {
        "x": 0,
        "y": 0,
        "z": 0
      }
    },
    "a9eaVwYEhOs7UTXxG6rscv": {
      "position": {
        "x": 479,
        "y": 325.5,
        "z": 5000
      },
      "rotation": {
        "x": 0,
        "y": 0,
        "z": 0,
        "w": 1
      },
      "viewCenter": {
        "x": 0,
        "y": 0,
        "z": 0
      }
    },
    "80XYhC+mNBbJdLfe5tNDGt": {
      "position": {
        "x": 479,
        "y": 325.5,
        "z": 5000
      },
      "rotation": {
        "x": 0,
        "y": 0,
        "z": 0,
        "w": 1
      },
      "viewCenter": {
        "x": 0,
        "y": 0,
        "z": 0
      }
    },
    "01fDZu5LxI2L66cHmvjd4a": {
      "position": {
        "x": 479,
        "y": 325.5,
        "z": 5000
      },
      "rotation": {
        "x": 0,
        "y": 0,
        "z": 0,
        "w": 1
      },
      "viewCenter": {
        "x": 0,
        "y": 0,
        "z": 0
      }
    },
    "03IE8pQupNIasGaVv86s9T": {
      "position": {
        "x": 479,
        "y": 325.5,
        "z": 5000
      },
      "rotation": {
        "x": 0,
        "y": 0,
        "z": 0,
        "w": 1
      },
      "viewCenter": {
        "x": 0,
        "y": 0,
        "z": 0
      }
    },
    "fbg84RWp9AtJIDRAPRAPmR": {
      "position": {
        "x": 479,
        "y": 325.5,
        "z": 5000
      },
      "rotation": {
        "x": 0,
        "y": 0,
        "z": 0,
        "w": 1
      },
      "viewCenter": {
        "x": 0,
        "y": 0,
        "z": 0
      }
    },
    "50lcDH+QVLN6cevh5dPe+R": {
      "position": {
        "x": 479,
        "y": 325.5,
        "z": 5000
      },
      "rotation": {
        "x": 0,
        "y": 0,
        "z": 0,
        "w": 1
      },
      "viewCenter": {
        "x": 0,
        "y": 0,
        "z": 0
      }
    },
    "6eilyRGFRJjpAAJO+bCdKL": {
      "position": {
        "x": 479,
        "y": 325.5,
        "z": 5000
      },
      "rotation": {
        "x": 0,
        "y": 0,
        "z": 0,
        "w": 1
      },
      "viewCenter": {
        "x": 0,
        "y": 0,
        "z": 0
      }
    },
    "c09W/PGHlCC79dxPZY/NWT": {
      "position": {
        "x": 479,
        "y": 325.5,
        "z": 5000
      },
      "rotation": {
        "x": 0,
        "y": 0,
        "z": 0,
        "w": 1
      },
      "viewCenter": {
        "x": 0,
        "y": 0,
        "z": 0
      }
    },
    "5dnGaeVtZNlZ1plPgAK/T3": {
      "position": {
        "x": 479,
        "y": 325.5,
        "z": 5000
      },
      "rotation": {
        "x": 0,
        "y": 0,
        "z": 0,
        "w": 1
      },
      "viewCenter": {
        "x": 0,
        "y": 0,
        "z": 0
      }
    },
    "b5qCLqy8dFN4G8HbmHVID9": {
      "position": {
        "x": 540,
        "y": 960,
        "z": 5000
      },
      "rotation": {
        "x": 0,
        "y": 0,
        "z": 0,
        "w": 1
      },
      "viewCenter": {
        "x": 0,
        "y": 0,
        "z": 0
      }
    },
    "88AK4WLCVF3ZQAPiaeJM9j": {
      "position": {
        "x": 479,
        "y": 325.5,
        "z": 5000
      },
      "rotation": {
        "x": 0,
        "y": 0,
        "z": 0,
        "w": 1
      },
      "viewCenter": {
        "x": 0,
        "y": 0,
        "z": 0
      }
    },
    "7esfnfhExMgJwVIJg5pKBh": {
      "position": {
        "x": 479,
        "y": 325.5,
        "z": 5000
      },
      "rotation": {
        "x": 0,
        "y": 0,
        "z": 0,
        "w": 1
      },
      "viewCenter": {
        "x": 0,
        "y": 0,
        "z": 0
      }
    },
    "a17zmEoWVDP78fD6Y18pVD": {
      "position": {
        "x": 479,
        "y": 325.5,
        "z": 5000
      },
      "rotation": {
        "x": 0,
        "y": 0,
        "z": 0,
        "w": 1
      },
      "viewCenter": {
        "x": 0,
        "y": 0,
        "z": 0
      }
    },
    "18DW6X/H1K06RnIGioWwVp": {
      "position": {
        "x": 479,
        "y": 325.5,
        "z": 5000
      },
      "rotation": {
        "x": 0,
        "y": 0,
        "z": 0,
        "w": 1
      },
      "viewCenter": {
        "x": 0,
        "y": 0,
        "z": 0
      }
    },
    "59whwnIVhDSL5PaFZGkmIW": {
      "position": {
        "x": 479,
        "y": 325.5,
        "z": 5000
      },
      "rotation": {
        "x": 0,
        "y": 0,
        "z": 0,
        "w": 1
      },
      "viewCenter": {
        "x": 0,
        "y": 0,
        "z": 0
      }
    },
    "5buBo8xOlEo6RA/suGiXS2": {
      "position": {
        "x": 479,
        "y": 325.5,
        "z": 5000
      },
      "rotation": {
        "x": 0,
        "y": 0,
        "z": 0,
        "w": 1
      },
      "viewCenter": {
        "x": 0,
        "y": 0,
        "z": 0
      }
    },
    "92bh2b/jFDV47T7hE+u0/k": {
      "position": {
        "x": 479,
        "y": 325.5,
        "z": 5000
      },
      "rotation": {
        "x": 0,
        "y": 0,
        "z": 0,
        "w": 1
      },
      "viewCenter": {
        "x": 0,
        "y": 0,
        "z": 0
      }
    },
    "28Ro7sRRpBLJb0f63d8DMv": {
      "position": {
        "x": 479,
        "y": 325.5,
        "z": 5000
      },
      "rotation": {
        "x": 0,
        "y": 0,
        "z": 0,
        "w": 1
      },
      "viewCenter": {
        "x": 0,
        "y": 0,
        "z": 0
      }
    },
    "3dAahJwlNHHIgyR+EOqaMM": {
      "position": {
        "x": 479,
        "y": 325.5,
        "z": 5000
      },
      "rotation": {
        "x": 0,
        "y": 0,
        "z": 0,
        "w": 1
      },
      "viewCenter": {
        "x": 0,
        "y": 0,
        "z": 0
      }
    },
    "23w/qU3IxEFLdiyjO06Doh": {
      "position": {
        "x": 479,
        "y": 325.5,
        "z": 5000
      },
      "rotation": {
        "x": 0,
        "y": 0,
        "z": 0,
        "w": 1
      },
      "viewCenter": {
        "x": 0,
        "y": 0,
        "z": 0
      }
    },
    "f3XWvpyjxP55imJPddfiUu": {
      "position": {
        "x": 479,
        "y": 325.5,
        "z": 5000
      },
      "rotation": {
        "x": 0,
        "y": 0,
        "z": 0,
        "w": 1
      },
      "viewCenter": {
        "x": 0,
        "y": 0,
        "z": 0
      }
    },
    "6fzobEBQdFfZCbbG1N8Ohj": {
      "position": {
        "x": 479,
        "y": 325.5,
        "z": 5000
      },
      "rotation": {
        "x": 0,
        "y": 0,
        "z": 0,
        "w": 1
      },
      "viewCenter": {
        "x": 0,
        "y": 0,
        "z": 0
      }
    },
    "5cQEJBF2tCjJsV6V0phyW3": {
      "position": {
        "x": 479,
        "y": 325.5,
        "z": 5000
      },
      "rotation": {
        "x": 0,
        "y": 0,
        "z": 0,
        "w": 1
      },
      "viewCenter": {
        "x": 0,
        "y": 0,
        "z": 0
      }
    },
    "eex6nQUJtDP7HmhGbaBVvq": {
      "position": {
        "x": 479,
        "y": 325.5,
        "z": 5000
      },
      "rotation": {
        "x": 0,
        "y": 0,
        "z": 0,
        "w": 1
      },
      "viewCenter": {
        "x": 0,
        "y": 0,
        "z": 0
      }
    },
    "e6wAj5KNVNIpb6+j3C3864": {
      "position": {
        "x": 479,
        "y": 325.5,
        "z": 5000
      },
      "rotation": {
        "x": 0,
        "y": 0,
        "z": 0,
        "w": 1
      },
      "viewCenter": {
        "x": 0,
        "y": 0,
        "z": 0
      }
    },
    "baC2IKMpZBc6CRXw9DsQKK": {
      "position": {
        "x": 479,
        "y": 325.5,
        "z": 5000
      },
      "rotation": {
        "x": 0,
        "y": 0,
        "z": 0,
        "w": 1
      },
      "viewCenter": {
        "x": 0,
        "y": 0,
        "z": 0
      }
    },
    "1c9Pvi5aBAObK6k/1Y2HIS": {
      "position": {
        "x": 479,
        "y": 325.5,
        "z": 5000
      },
      "rotation": {
        "x": 0,
        "y": 0,
        "z": 0,
        "w": 1
      },
      "viewCenter": {
        "x": 0,
        "y": 0,
        "z": 0
      }
    },
    "4eipnH5YRClYJkNKnRKW2V": {
      "position": {
        "x": 479,
        "y": 325.5,
        "z": 5000
      },
      "rotation": {
        "x": 0,
        "y": 0,
        "z": 0,
        "w": 1
      },
      "viewCenter": {
        "x": 0,
        "y": 0,
        "z": 0
      }
    },
    "89FSPBFp1JGrSadaPzGwV2": {
      "position": {
        "x": 479,
        "y": 325.5,
        "z": 5000
      },
      "rotation": {
        "x": 0,
        "y": 0,
        "z": 0,
        "w": 1
      },
      "viewCenter": {
        "x": 0,
        "y": 0,
        "z": 0
      }
    },
    "f9NSZC111KTrwktgO+vw0I": {
      "position": {
        "x": 479,
        "y": 325.5,
        "z": 5000
      },
      "rotation": {
        "x": 0,
        "y": 0,
        "z": 0,
        "w": 1
      },
      "viewCenter": {
        "x": 0,
        "y": 0,
        "z": 0
      }
    },
    "a5BszkTrdFyL6R8LmuJZIV": {
      "position": {
        "x": 479,
        "y": 325.5,
        "z": 5000
      },
      "rotation": {
        "x": 0,
        "y": 0,
        "z": 0,
        "w": 1
      },
      "viewCenter": {
        "x": 0,
        "y": 0,
        "z": 0
      }
    },
    "272CDJDmJCDIFF1VO5LBr2": {
      "position": {
        "x": 309.1542048772642,
        "y": 461.26687675525596,
        "z": 5000
      },
      "rotation": {
        "x": 0,
        "y": 0,
        "z": 0,
        "w": 1
      },
      "viewCenter": {
        "x": 0,
        "y": 0,
        "z": 0
      }
    },
    "27BIvBablPmqemcfOJncsk": {
      "position": {
        "x": 479,
        "y": 325.5,
        "z": 5000
      },
      "rotation": {
        "x": 0,
        "y": 0,
        "z": 0,
        "w": 1
      },
      "viewCenter": {
        "x": 0,
        "y": 0,
        "z": 0
      }
    },
    "acujibyXxGObPM0mPE3j2t": {
      "position": {
        "x": 479,
        "y": 325.5,
        "z": 5000
      },
      "rotation": {
        "x": 0,
        "y": 0,
        "z": 0,
        "w": 1
      },
      "viewCenter": {
        "x": 0,
        "y": 0,
        "z": 0
      }
    },
    "65RWyhvPRIJbCn8husHUU1": {
      "position": {
        "x": 479,
        "y": 325.5,
        "z": 5000
      },
      "rotation": {
        "x": 0,
        "y": 0,
        "z": 0,
        "w": 1
      },
      "viewCenter": {
        "x": 0,
        "y": 0,
        "z": 0
      }
    },
    "43KrT6SEBKvIZ3khrbiCDj": {
      "position": {
        "x": 479,
        "y": 325.5,
        "z": 5000
      },
      "rotation": {
        "x": 0,
        "y": 0,
        "z": 0,
        "w": 1
      },
      "viewCenter": {
        "x": 0,
        "y": 0,
        "z": 0
      }
    },
    "95JkUcIz5HX7d0BJ+xZF5P": {
      "position": {
        "x": 479,
        "y": 325.5,
        "z": 5000
      },
      "rotation": {
        "x": 0,
        "y": 0,
        "z": 0,
        "w": 1
      },
      "viewCenter": {
        "x": 0,
        "y": 0,
        "z": 0
      }
    },
    "a9w1gcw49C65+Djzwxo1Kq": {
      "position": {
        "x": 479,
        "y": 325.5,
        "z": 5000
      },
      "rotation": {
        "x": 0,
        "y": 0,
        "z": 0,
        "w": 1
      },
      "viewCenter": {
        "x": 0,
        "y": 0,
        "z": 0
      }
    },
    "17sq1SxlhBd7txL5wq3R9B": {
      "position": {
        "x": 479,
        "y": 325.5,
        "z": 5000
      },
      "rotation": {
        "x": 0,
        "y": 0,
        "z": 0,
        "w": 1
      },
      "viewCenter": {
        "x": 0,
        "y": 0,
        "z": 0
      }
    },
    "6cpM6972xI3Y4JN2AHXZSz": {
      "position": {
        "x": 479,
        "y": 325.5,
        "z": 5000
      },
      "rotation": {
        "x": 0,
        "y": 0,
        "z": 0,
        "w": 1
      },
      "viewCenter": {
        "x": 0,
        "y": 0,
        "z": 0
      }
    },
    "b6Y/VOgKNI0Zg5/zTfqalt": {
      "position": {
        "x": 479,
        "y": 325.5,
        "z": 5000
      },
      "rotation": {
        "x": 0,
        "y": 0,
        "z": 0,
        "w": 1
      },
      "viewCenter": {
        "x": 0,
        "y": 0,
        "z": 0
      }
    },
    "ddDGHVpKlNaLpMOS0YtuH7": {
      "position": {
        "x": 479,
        "y": 325.5,
        "z": 5000
      },
      "rotation": {
        "x": 0,
        "y": 0,
        "z": 0,
        "w": 1
      },
      "viewCenter": {
        "x": 0,
        "y": 0,
        "z": 0
      }
    },
    "c2VN7TOoxCRLzv6fcUPN6O": {
      "position": {
        "x": 479,
        "y": 325.5,
        "z": 5000
      },
      "rotation": {
        "x": 0,
        "y": 0,
        "z": 0,
        "w": 1
      },
      "viewCenter": {
        "x": 0,
        "y": 0,
        "z": 0
      }
    },
    "1eeXwk5kVDjqcLMmJH9pp5": {
      "position": {
        "x": 479,
        "y": 325.5,
        "z": 5000
      },
      "rotation": {
        "x": 0,
        "y": 0,
        "z": 0,
        "w": 1
      },
      "viewCenter": {
        "x": 0,
        "y": 0,
        "z": 0
      }
    },
    "2fnHNfRbJC5ZFa7DamYfyX": {
      "position": {
        "x": 479,
        "y": 325.5,
        "z": 5000
      },
      "rotation": {
        "x": 0,
        "y": 0,
        "z": 0,
        "w": 1
      },
      "viewCenter": {
        "x": 0,
        "y": 0,
        "z": 0
      }
    },
    "6e+1wSwJ9Myr2l0+0Uqj4a": {
      "position": {
        "x": 479,
        "y": 325.5,
        "z": 5000
      },
      "rotation": {
        "x": 0,
        "y": 0,
        "z": 0,
        "w": 1
      },
      "viewCenter": {
        "x": 0,
        "y": 0,
        "z": 0
      }
    },
    "0aMBw6K91LjqrVOQ1MvgJd": {
      "position": {
        "x": 479,
        "y": 325.5,
        "z": 5000
      },
      "rotation": {
        "x": 0,
        "y": 0,
        "z": 0,
        "w": 1
      },
      "viewCenter": {
        "x": 0,
        "y": 0,
        "z": 0
      }
    },
    "7eM376OcRJWpApABXpx01l": {
      "position": {
        "x": 479,
        "y": 325.5,
        "z": 5000
      },
      "rotation": {
        "x": 0,
        "y": 0,
        "z": 0,
        "w": 1
      },
      "viewCenter": {
        "x": 0,
        "y": 0,
        "z": 0
      }
    },
    "17CX7f7e9EOLub7VUS4eQ/": {
      "position": {
        "x": 479,
        "y": 325.5,
        "z": 5000
      },
      "rotation": {
        "x": 0,
        "y": 0,
        "z": 0,
        "w": 1
      },
      "viewCenter": {
        "x": 0,
        "y": 0,
        "z": 0
      }
    },
    "9eJ9a+Pr9EYqjRsvJ8alT9": {
      "position": {
        "x": 479,
        "y": 325.5,
        "z": 5000
      },
      "rotation": {
        "x": 0,
        "y": 0,
        "z": 0,
        "w": 1
      },
      "viewCenter": {
        "x": 0,
        "y": 0,
        "z": 0
      }
    },
    "86hZI4ufRLeZfBibrPafzo": {
      "position": {
        "x": 479,
        "y": 325.5,
        "z": 5000
      },
      "rotation": {
        "x": 0,
        "y": 0,
        "z": 0,
        "w": 1
      },
      "viewCenter": {
        "x": 0,
        "y": 0,
        "z": 0
      }
    },
    "5eZf1L87RD1L0kgLrUsOOJ": {
      "position": {
        "x": 479,
        "y": 325.5,
        "z": 5000
      },
      "rotation": {
        "x": 0,
        "y": 0,
        "z": 0,
        "w": 1
      },
      "viewCenter": {
        "x": 0,
        "y": 0,
        "z": 0
      }
    },
    "195QYP9cZFI7sw8jtimV0d": {
      "position": {
        "x": 479,
        "y": 325.5,
        "z": 5000
      },
      "rotation": {
        "x": 0,
        "y": 0,
        "z": 0,
        "w": 1
      },
      "viewCenter": {
        "x": 0,
        "y": 0,
        "z": 0
      }
    },
    "08bWk9eLJP6YuUFn5jjK9g": {
      "position": {
        "x": 479,
        "y": 325.5,
        "z": 5000
      },
      "rotation": {
        "x": 0,
        "y": 0,
        "z": 0,
        "w": 1
      },
      "viewCenter": {
        "x": 0,
        "y": 0,
        "z": 0
      }
    },
    "61v5T32L9DWIYgpywG94pW": {
      "position": {
        "x": 479,
        "y": 325.5,
        "z": 5000
      },
      "rotation": {
        "x": 0,
        "y": 0,
        "z": 0,
        "w": 1
      },
      "viewCenter": {
        "x": 0,
        "y": 0,
        "z": 0
      }
    },
    "0ab8d83EFN5p8MSu1RgpOM": {
      "position": {
        "x": 479,
        "y": 325.5,
        "z": 5000
      },
      "rotation": {
        "x": 0,
        "y": 0,
        "z": 0,
        "w": 1
      },
      "viewCenter": {
        "x": 0,
        "y": 0,
        "z": 0
      }
    },
    "32tnWspqFEG6Y813ft5jyP": {
      "position": {
        "x": 479,
        "y": 325.5,
        "z": 5000
      },
      "rotation": {
        "x": 0,
        "y": 0,
        "z": 0,
        "w": 1
      },
      "viewCenter": {
        "x": 0,
        "y": 0,
        "z": 0
      }
    },
    "63tD8uiVZIZr3PkIGff4M+": {
      "position": {
        "x": 479,
        "y": 325.5,
        "z": 5000
      },
      "rotation": {
        "x": 0,
        "y": 0,
        "z": 0,
        "w": 1
      },
      "viewCenter": {
        "x": 0,
        "y": 0,
        "z": 0
      }
    },
    "6bAtxHbfBOrrhHT/WPHS8l": {
      "position": {
        "x": 479,
        "y": 325.5,
        "z": 5000
      },
      "rotation": {
        "x": 0,
        "y": 0,
        "z": 0,
        "w": 1
      },
      "viewCenter": {
        "x": 0,
        "y": 0,
        "z": 0
      }
    },
    "9098xNnyZOzr4ZjkMNbDqh": {
      "position": {
        "x": 479,
        "y": 325.5,
        "z": 5000
      },
      "rotation": {
        "x": 0,
        "y": 0,
        "z": 0,
        "w": 1
      },
      "viewCenter": {
        "x": 0,
        "y": 0,
        "z": 0
      }
    },
    "bcQjMAq4JLtKqLGbZ1JnTC": {
      "position": {
        "x": 479,
        "y": 325.5,
        "z": 5000
      },
      "rotation": {
        "x": 0,
        "y": 0,
        "z": 0,
        "w": 1
      },
      "viewCenter": {
        "x": 0,
        "y": 0,
        "z": 0
      }
    },
    "10KbaMAGdKTb1lpixZkKgP": {
      "position": {
        "x": 479,
        "y": 325.5,
        "z": 5000
      },
      "rotation": {
        "x": 0,
        "y": 0,
        "z": 0,
        "w": 1
      },
      "viewCenter": {
        "x": 0,
        "y": 0,
        "z": 0
      }
    },
    "a5ndcV/LNCp4vGlv0N9ymy": {
      "position": {
        "x": 479,
        "y": 325.5,
        "z": 5000
      },
      "rotation": {
        "x": 0,
        "y": 0,
        "z": 0,
        "w": 1
      },
      "viewCenter": {
        "x": 0,
        "y": 0,
        "z": 0
      }
    },
    "c8xy7LBz1KdaFZqcikUNOj": {
      "position": {
        "x": 661.4062222905941,
        "y": 1739.5485489720345,
        "z": 5000
      },
      "rotation": {
        "x": 0,
        "y": 0,
        "z": 0,
        "w": 1
      },
      "viewCenter": {
        "x": 0,
        "y": 0,
        "z": 0
      }
    },
    "efS3WuZVlJhqCieaDlO7ia": {
      "position": {
        "x": 479,
        "y": 326,
        "z": 5000
      },
      "rotation": {
        "x": 0,
        "y": 0,
        "z": 0,
        "w": 1
      },
      "viewCenter": {
        "x": 0,
        "y": 0,
        "z": 0
      }
    },
    "08iMH2xvlDTL647P4H82yM": {
      "position": {
        "x": 479,
        "y": 326.00000000000006,
        "z": 5000
      },
      "rotation": {
        "x": 0,
        "y": 0,
        "z": 0,
        "w": 1
      },
      "viewCenter": {
        "x": 0,
        "y": 0,
        "z": 0
      }
    },
    "f39XxwN35Jh4BjAqDCNcTT": {
      "position": {
        "x": 479,
        "y": 326.00000000000006,
        "z": 5000
      },
      "rotation": {
        "x": 0,
        "y": 0,
        "z": 0,
        "w": 1
      },
      "viewCenter": {
        "x": 0,
        "y": 0,
        "z": 0
      }
    },
    "25JQnDRvlDKa5jMogDDZ/c": {
      "position": {
        "x": 479,
        "y": 326.00000000000006,
        "z": 5000
      },
      "rotation": {
        "x": 0,
        "y": 0,
        "z": 0,
        "w": 1
      },
      "viewCenter": {
        "x": 0,
        "y": 0,
        "z": 0
      }
    },
    "casatqwjdCJ5cZDI7rc2zN": {
      "position": {
        "x": 479,
        "y": 326.00000000000006,
        "z": 5000
      },
      "rotation": {
        "x": 0,
        "y": 0,
        "z": 0,
        "w": 1
      },
      "viewCenter": {
        "x": 0,
        "y": 0,
        "z": 0
      }
    },
    "84oL0SSklDRJ7KCnFxQpTB": {
      "position": {
        "x": 479,
        "y": 326.00000000000006,
        "z": 5000
      },
      "rotation": {
        "x": 0,
        "y": 0,
        "z": 0,
        "w": 1
      },
      "viewCenter": {
        "x": 0,
        "y": 0,
        "z": 0
      }
    },
    "a2R8hl27FMiZAd3b/sDyFR": {
      "position": {
        "x": 479,
        "y": 326.00000000000006,
        "z": 5000
      },
      "rotation": {
        "x": 0,
        "y": 0,
        "z": 0,
        "w": 1
      },
      "viewCenter": {
        "x": 0,
        "y": 0,
        "z": 0
      }
    },
    "4bpJON+atON4G933Pwgt5n": {
      "position": {
        "x": 479,
        "y": 326.00000000000006,
        "z": 5000
      },
      "rotation": {
        "x": 0,
        "y": 0,
        "z": 0,
        "w": 1
      },
      "viewCenter": {
        "x": 0,
        "y": 0,
        "z": 0
      }
    },
    "aa9eURHVlFJIViYj4XDIFk": {
      "position": {
        "x": 479,
        "y": 326.00000000000006,
        "z": 5000
      },
      "rotation": {
        "x": 0,
        "y": 0,
        "z": 0,
        "w": 1
      },
      "viewCenter": {
        "x": 0,
        "y": 0,
        "z": 0
      }
    },
    "eat3pH+IFDz7CsBe15IrrN": {
      "position": {
        "x": 479,
        "y": 326.00000000000006,
        "z": 5000
      },
      "rotation": {
        "x": 0,
        "y": 0,
        "z": 0,
        "w": 1
      },
      "viewCenter": {
        "x": 0,
        "y": 0,
        "z": 0
      }
    },
    "c8c9M0M6RNoZDQgZz90482": {
      "position": {
        "x": 545.5591838779292,
        "y": 852.492638948565,
        "z": 5000
      },
      "rotation": {
        "x": 0,
        "y": 0,
        "z": 0,
        "w": 1
      },
      "viewCenter": {
        "x": 0,
        "y": 0,
        "z": 0
      }
    },
    "ccHv7LY0FNP4I0rrW9w+3d": {
      "position": {
        "x": 479,
        "y": 326,
        "z": 5000
      },
      "rotation": {
        "x": 0,
        "y": 0,
        "z": 0,
        "w": 1
      },
      "viewCenter": {
        "x": 0,
        "y": 0,
        "z": 0
      }
    },
    "2cWFKseJFBi57xawi/mkCw": {
      "position": {
        "x": 479,
        "y": 326.00000000000006,
        "z": 5000
      },
      "rotation": {
        "x": 0,
        "y": 0,
        "z": 0,
        "w": 1
      },
      "viewCenter": {
        "x": 0,
        "y": 0,
        "z": 0
      }
    },
    "fac9KgSCVCk7/wcb6sZg7X": {
      "position": {
        "x": 479,
        "y": 326.00000000000006,
        "z": 5000
      },
      "rotation": {
        "x": 0,
        "y": 0,
        "z": 0,
        "w": 1
      },
      "viewCenter": {
        "x": 0,
        "y": 0,
        "z": 0
      }
    },
    "ecnMxY3Z5Fc5H+tSDr9vIu": {
      "position": {
        "x": 479,
        "y": 326.00000000000006,
        "z": 5000
      },
      "rotation": {
        "x": 0,
        "y": 0,
        "z": 0,
        "w": 1
      },
      "viewCenter": {
        "x": 0,
        "y": 0,
        "z": 0
      }
    },
    "76h8FY9mpIK7MsHbMlhX4u": {
      "position": {
        "x": 479,
        "y": 326.00000000000006,
        "z": 5000
      },
      "rotation": {
        "x": 0,
        "y": 0,
        "z": 0,
        "w": 1
      },
      "viewCenter": {
        "x": 0,
        "y": 0,
        "z": 0
      }
    },
    "f2vzQ07BdE14w9PWQOuFJw": {
      "position": {
        "x": 479,
        "y": 326.00000000000006,
        "z": 5000
      },
      "rotation": {
        "x": 0,
        "y": 0,
        "z": 0,
        "w": 1
      },
      "viewCenter": {
        "x": 0,
        "y": 0,
        "z": 0
      }
    },
    "cfWbHCCilLiZp2Ce+1DHE1": {
      "position": {
        "x": 479,
        "y": 326.00000000000006,
        "z": 5000
      },
      "rotation": {
        "x": 0,
        "y": 0,
        "z": 0,
        "w": 1
      },
      "viewCenter": {
        "x": 0,
        "y": 0,
        "z": 0
      }
    },
    "20rZRrqNlBH6cGgWdTqCYh": {
      "position": {
        "x": 479,
        "y": 326.00000000000006,
        "z": 5000
      },
      "rotation": {
        "x": 0,
        "y": 0,
        "z": 0,
        "w": 1
      },
      "viewCenter": {
        "x": 0,
        "y": 0,
        "z": 0
      }
    },
    "ecthJtJb9NLobx3YjHqmXn": {
      "position": {
        "x": 479,
        "y": 326.00000000000006,
        "z": 5000
      },
      "rotation": {
        "x": 0,
        "y": 0,
        "z": 0,
        "w": 1
      },
      "viewCenter": {
        "x": 0,
        "y": 0,
        "z": 0
      }
    },
    "cf49L8yW9BTIM3IAXJEjQk": {
      "position": {
        "x": 479,
        "y": 326.00000000000006,
        "z": 5000
      },
      "rotation": {
        "x": 0,
        "y": 0,
        "z": 0,
        "w": 1
      },
      "viewCenter": {
        "x": 0,
        "y": 0,
        "z": 0
      }
    },
    "1cmfLfPxxCjpP0EWm6mxbP": {
      "position": {
        "x": 479,
        "y": 326.00000000000006,
        "z": 5000
      },
      "rotation": {
        "x": 0,
        "y": 0,
        "z": 0,
        "w": 1
      },
      "viewCenter": {
        "x": 0,
        "y": 0,
        "z": 0
      }
    },
    "91BASSUDNDx5hmiUL4YjPy": {
      "position": {
        "x": 479,
        "y": 326.00000000000006,
        "z": 5000
      },
      "rotation": {
        "x": 0,
        "y": 0,
        "z": 0,
        "w": 1
      },
      "viewCenter": {
        "x": 0,
        "y": 0,
        "z": 0
      }
    },
    "148K9yp8lC2JeH25GAGrGc": {
      "position": {
        "x": 595.3007563949324,
        "y": 555.4269838070101,
        "z": 5000
      },
      "rotation": {
        "x": 0,
        "y": 0,
        "z": 0,
        "w": 1
      },
      "viewCenter": {
        "x": 0,
        "y": 0,
        "z": 0
      }
    },
    "14QDml5axAW7FksJA8ybf8": {
      "position": {
        "x": 479,
        "y": 326.00000000000006,
        "z": 5000
      },
      "rotation": {
        "x": 0,
        "y": 0,
        "z": 0,
        "w": 1
      },
      "viewCenter": {
        "x": 0,
        "y": 0,
        "z": 0
      }
    },
    "6bFpHVoS5BRac7Za35ireH": {
      "position": {
        "x": 479,
        "y": 326.00000000000006,
        "z": 5000
      },
      "rotation": {
        "x": 0,
        "y": 0,
        "z": 0,
        "w": 1
      },
      "viewCenter": {
        "x": 0,
        "y": 0,
        "z": 0
      }
    },
    "90IwH5C5pNV7opAILVSwSe": {
      "position": {
        "x": 479,
        "y": 326.00000000000006,
        "z": 5000
      },
      "rotation": {
        "x": 0,
        "y": 0,
        "z": 0,
        "w": 1
      },
      "viewCenter": {
        "x": 0,
        "y": 0,
        "z": 0
      }
    },
    "12e8WgyItEOYirIb36V0RC": {
      "position": {
        "x": 479,
        "y": 326.00000000000006,
        "z": 5000
      },
      "rotation": {
        "x": 0,
        "y": 0,
        "z": 0,
        "w": 1
      },
      "viewCenter": {
        "x": 0,
        "y": 0,
        "z": 0
      }
    },
    "dadntH3WdCNpqhAMvCWEWX": {
      "position": {
        "x": 479,
        "y": 326.00000000000006,
        "z": 5000
      },
      "rotation": {
        "x": 0,
        "y": 0,
        "z": 0,
        "w": 1
      },
      "viewCenter": {
        "x": 0,
        "y": 0,
        "z": 0
      }
    },
    "d0Wb4TZs5D15Y4vzLpt6hK": {
      "position": {
        "x": 479,
        "y": 326.00000000000006,
        "z": 5000
      },
      "rotation": {
        "x": 0,
        "y": 0,
        "z": 0,
        "w": 1
      },
      "viewCenter": {
        "x": 0,
        "y": 0,
        "z": 0
      }
    },
    "ffnvO6tBpCxJBrb710tb6g": {
      "position": {
        "x": 289.17326328807235,
        "y": 393.00478476932386,
        "z": 5000
      },
      "rotation": {
        "x": 0,
        "y": 0,
        "z": 0,
        "w": 1
      },
      "viewCenter": {
        "x": 0,
        "y": 0,
        "z": 0
      }
    },
    "58Q8hjotJODaTf9LiXEEDS": {
      "position": {
        "x": 720.2564406243605,
        "y": 740.5201571848928,
        "z": 5000
      },
      "rotation": {
        "x": 0,
        "y": 0,
        "z": 0,
        "w": 1
      },
      "viewCenter": {
        "x": 0,
        "y": 0,
        "z": 0
      }
    },
    "cdZ/2fduZDYql/yMA6Vrji": {
      "position": {
        "x": 1193.2871731303976,
        "y": 498.0802137837575,
        "z": 5000
      },
      "rotation": {
        "x": 0,
        "y": 0,
        "z": 0,
        "w": 1
      },
      "viewCenter": {
        "x": 0,
        "y": 0,
        "z": 0
      }
    },
    "76wZOOUwVCv5/UyGQS6hmg": {
      "position": {
        "x": 1213.2496949727877,
        "y": 487.9837074754487,
        "z": 5000
      },
      "rotation": {
        "x": 0,
        "y": 0,
        "z": 0,
        "w": 1
      },
      "viewCenter": {
        "x": 0,
        "y": 0,
        "z": 0
      }
    },
    "7bbCBONVxEurzIQjoogNXr": {
      "position": {
        "x": 607.1373995169442,
        "y": 746.9247204917447,
        "z": 5000
      },
      "rotation": {
        "x": 0,
        "y": 0,
        "z": 0,
        "w": 1
      },
      "viewCenter": {
        "x": 0,
        "y": 0,
        "z": 0
      }
    },
    "a2LHDjYRFHuIGrGDOg+cZ0": {
      "position": {
        "x": 548.063137392203,
        "y": 672.9686779714414,
        "z": 5000
      },
      "rotation": {
        "x": 0,
        "y": 0,
        "z": 0,
        "w": 1
      },
      "viewCenter": {
        "x": 0,
        "y": 0,
        "z": 0
      }
    },
    "e35oLhxZxJYKiHNVGT11l9": {
      "position": {
        "x": 783.6486974999269,
        "y": 236.78516386888356,
        "z": 5000
      },
      "rotation": {
        "x": 0,
        "y": 0,
        "z": 0,
        "w": 1
      },
      "viewCenter": {
        "x": 0,
        "y": 0,
        "z": 0
      }
    },
    "14G/pqqERPqKM6LAwrWzVy": {
      "position": {
        "x": 682.2679696328166,
        "y": 845.1083348012972,
        "z": 5000
      },
      "rotation": {
        "x": 0,
        "y": 0,
        "z": 0,
        "w": 1
      },
      "viewCenter": {
        "x": 0,
        "y": 0,
        "z": 0
      }
    },
    "e8bhYlyQVBYZvnMJu/IxBa": {
      "position": {
        "x": 784.7865722014341,
        "y": 705.2465151532895,
        "z": 5000
      },
      "rotation": {
        "x": 0,
        "y": 0,
        "z": 0,
        "w": 1
      },
      "viewCenter": {
        "x": 0,
        "y": 0,
        "z": 0
      }
    },
    "70e7AcnqRBR6CdDP+aoxCf": {
      "position": {
        "x": 593.6162416875047,
        "y": 841.9479083956099,
        "z": 5000
      },
      "rotation": {
        "x": 0,
        "y": 0,
        "z": 0,
        "w": 1
      },
      "viewCenter": {
        "x": 0,
        "y": 0,
        "z": 0
      }
    },
    "50EvA21rFGkY1i9z/0B3HL": {
      "position": {
        "x": 479,
        "y": 326.0000000000001,
        "z": 5000
      },
      "rotation": {
        "x": 0,
        "y": 0,
        "z": 0,
        "w": 1
      },
      "viewCenter": {
        "x": 0,
        "y": 0,
        "z": 0
      }
    },
    "05teZAAgxJ0YZDc0sTSB6/": {
      "position": {
        "x": 1349.6974069590992,
        "y": 707.7480528048095,
        "z": 5000
      },
      "rotation": {
        "x": 0,
        "y": 0,
        "z": 0,
        "w": 1
      },
      "viewCenter": {
        "x": 0,
        "y": 0,
        "z": 0
      }
    },
    "81L+1LNbhFfpMBJ3ewO0R9": {
      "position": {
        "x": 479,
        "y": 326.00000000000006,
        "z": 5000
      },
      "rotation": {
        "x": 0,
        "y": 0,
        "z": 0,
        "w": 1
      },
      "viewCenter": {
        "x": 0,
        "y": 0,
        "z": 0
      }
    },
    "9aAZFtExdMP6iJQWTY4ImK": {
      "position": {
        "x": 640.5,
        "y": 360.5,
        "z": 5000
      },
      "rotation": {
        "x": 0,
        "y": 0,
        "z": 0,
        "w": 1
      },
      "viewCenter": {
        "x": 0,
        "y": 0,
        "z": 0
      }
    },
    "546DMS+yhCLpSMH6ICAXUt": {
      "position": {
        "x": 727.7552082039781,
        "y": 630.8311930341896,
        "z": 5000
      },
      "rotation": {
        "x": 0,
        "y": 0,
        "z": 0,
        "w": 1
      },
      "viewCenter": {
        "x": 0,
        "y": 0,
        "z": 0
      }
    },
    "ecAO5iRg5NhoRdoOuwGUBX": {
      "position": {
        "x": 861.2479131960012,
        "y": 538.1210339146077,
        "z": 5000
      },
      "rotation": {
        "x": 0,
        "y": 0,
        "z": 0,
        "w": 1
      },
      "viewCenter": {
        "x": 0,
        "y": 0,
        "z": 0
      }
    },
    "f6Xb2yp9hHeac7a2oamyQ8": {
      "position": {
        "x": 779.5791942806494,
        "y": 730.3696122056908,
        "z": 5000
      },
      "rotation": {
        "x": 0,
        "y": 0,
        "z": 0,
        "w": 1
      },
      "viewCenter": {
        "x": 0,
        "y": 0,
        "z": 0
      }
    },
    "06uc6btABMEJyyR/PqKMhK": {
      "position": {
        "x": 740.7918917101742,
        "y": 189.82658487117897,
        "z": 5000
      },
      "rotation": {
        "x": 0,
        "y": 0,
        "z": 0,
        "w": 1
      },
      "viewCenter": {
        "x": 0,
        "y": 0,
        "z": 0
      }
    },
    "8ciVXJSABHaZTgHqLE1iDg": {
      "position": {
        "x": 670.5340089645206,
        "y": 643.9318327873137,
        "z": 5000
      },
      "rotation": {
        "x": 0,
        "y": 0,
        "z": 0,
        "w": 1
      },
      "viewCenter": {
        "x": 0,
        "y": 0,
        "z": 0
      }
    },
    "f0MW94rAFPV718wWxepCbF": {
      "position": {
        "x": 492.9049332220794,
        "y": 559.633417126347,
        "z": 5000
      },
      "rotation": {
        "x": 0,
        "y": 0,
        "z": 0,
        "w": 1
      },
      "viewCenter": {
        "x": 0,
        "y": 0,
        "z": 0
      }
    },
    "43SB8gzr1Fy50PhzFD4iEH": {
      "position": {
        "x": 552.7405071171024,
        "y": 1621.5592995158374,
        "z": 5000
      },
      "rotation": {
        "x": 0,
        "y": 0,
        "z": 0,
        "w": 1
      },
      "viewCenter": {
        "x": 0,
        "y": 0,
        "z": 0
      }
    },
    "89fB4CCXdG0YSaJzTgcfNr": {
      "position": {
        "x": 606.6830006376392,
        "y": 901.412462681354,
        "z": 5000
      },
      "rotation": {
        "x": 0,
        "y": 0,
        "z": 0,
        "w": 1
      },
      "viewCenter": {
        "x": 0,
        "y": 0,
        "z": 0
      }
    },
    "9eQi3ErxFOVIdtQXJ/ySjp": {
      "position": {
        "x": 479,
        "y": 326.0000000000001,
        "z": 5000
      },
      "rotation": {
        "x": 0,
        "y": 0,
        "z": 0,
        "w": 1
      },
      "viewCenter": {
        "x": 0,
        "y": 0,
        "z": 0
      }
    },
    "5dmOY/SEFOe6jXLKQYF0vt": {
      "position": {
        "x": 479,
        "y": 326.00000000000006,
        "z": 5000
      },
      "rotation": {
        "x": 0,
        "y": 0,
        "z": 0,
        "w": 1
      },
      "viewCenter": {
        "x": 0,
        "y": 0,
        "z": 0
      }
    },
    "08sLpKDsBOTZNbRtDsz1y7": {
      "position": {
        "x": 479,
        "y": 326.00000000000006,
        "z": 5000
      },
      "rotation": {
        "x": 0,
        "y": 0,
        "z": 0,
        "w": 1
      },
      "viewCenter": {
        "x": 0,
        "y": 0,
        "z": 0
      }
    },
    "cbap0S3/FKdqeYJ+KW+866": {
      "position": {
        "x": 479,
        "y": 326,
        "z": 5000
      },
      "rotation": {
        "x": 0,
        "y": 0,
        "z": 0,
        "w": 1
      },
      "viewCenter": {
        "x": 0,
        "y": 0,
        "z": 0
      }
    },
    "e9Wxe6cbJMx4+qgiLmdPwk": {
      "position": {
        "x": 749.6302769098145,
        "y": 613.989086014176,
        "z": 5000
      },
      "rotation": {
        "x": 0,
        "y": 0,
        "z": 0,
        "w": 1
      },
      "viewCenter": {
        "x": 0,
        "y": 0,
        "z": 0
      }
    },
    "e1J5HvM4lHYbR7a8TZ4OVF": {
      "position": {
        "x": 1068.8266659153455,
        "y": 1075.051609465008,
        "z": 5000
      },
      "rotation": {
        "x": 0,
        "y": 0,
        "z": 0,
        "w": 1
      },
      "viewCenter": {
        "x": 0,
        "y": 0,
        "z": 0
      }
    },
    "0djdDTzrxDgYXJC9HZ0mEr": {
      "position": {
        "x": 705.3161198306004,
        "y": 877.5701121417342,
        "z": 5000
      },
      "rotation": {
        "x": 0,
        "y": 0,
        "z": 0,
        "w": 1
      },
      "viewCenter": {
        "x": 0,
        "y": 0,
        "z": 0
      }
    },
    "a7SZU0QrtFIpV2nvyZ+6Dr": {
      "position": {
        "x": 836.6175848239653,
        "y": 604.8348783527499,
        "z": 5000
      },
      "rotation": {
        "x": 0,
        "y": 0,
        "z": 0,
        "w": 1
      },
      "viewCenter": {
        "x": 0,
        "y": 0,
        "z": 0
      }
    },
    "2eMjkEl0ZDrq0E1re5l+GY": {
      "position": {
        "x": 779.1339708133492,
        "y": 1540.4103964869073,
        "z": 5000
      },
      "rotation": {
        "x": 0,
        "y": 0,
        "z": 0,
        "w": 1
      },
      "viewCenter": {
        "x": 0,
        "y": 0,
        "z": 0
      }
    },
    "0ecN5zjaRCKaPDOAIWYNJ7": {
      "position": {
        "x": 985.0802190372972,
        "y": 1759.9926505767967,
        "z": 5000
      },
      "rotation": {
        "x": 0,
        "y": 0,
        "z": 0,
        "w": 1
      },
      "viewCenter": {
        "x": 0,
        "y": 0,
        "z": 0
      }
    },
    "d1UWyYxNFOqqHbEflxKDjL": {
      "position": {
        "x": 1060.3032556713274,
        "y": 1693.8050183614805,
        "z": 5000
      },
      "rotation": {
        "x": 0,
        "y": 0,
        "z": 0,
        "w": 1
      },
      "viewCenter": {
        "x": 0,
        "y": 0,
        "z": 0
      }
    },
    "d2EoKZ3iFKgo3/jKeG3iYD": {
      "position": {
        "x": 913.9735369905625,
        "y": 628.6534958725856,
        "z": 5000
      },
      "rotation": {
        "x": 0,
        "y": 0,
        "z": 0,
        "w": 1
      },
      "viewCenter": {
        "x": 0,
        "y": 0,
        "z": 0
      }
    },
    "e4MCMBuchMM5eBmuYdFqli": {
      "position": {
        "x": 507.3863472849612,
        "y": 360.5313113012533,
        "z": 5000
      },
      "rotation": {
        "x": 0,
        "y": 0,
        "z": 0,
        "w": 1
      },
      "viewCenter": {
        "x": 0,
        "y": 0,
        "z": 0
      }
    }
  },
  "camera-uuids": [
    "f003f78a-c18a-49b4-afe2-1f8df294b9b1"
  ],
  "__version__": "1.0.0",
  "builder": {
    "taskOptionsMap": {},
    "__version__": "1.3.4"
  },
  "": {
    "sculpt_brush_rotate": 0
  },
  "scene": {
    "native": false
  },
  "snap-configs": {
    "position": {
      "x": 1,
      "y": 1,
      "z": 1
    },
    "rotation": 1,
    "scale": 1,
    "isPositionSnapEnabled": false,
    "isRotationSnapEnabled": false,
    "isScaleSnapEnabled": false
  },
  "rect-snap-configs": {
    "enableSnapping": true,
    "snapThreshold": 4
  }
}
